Workbook

Sheet Donnees SOMIDA
A1: DONNEES SOMIDA - PARAMETRES ET REFERENTIELS
A2: Paramètre | B2: Valeur | C2: Unité / devise | D2: Commentaire
A3: Exercice | B3: 2024 | C3: année | D3: Exercice budgétaire
A4: Inflation annuelle | B4: 0.065 | C4: % | D4: Hypothèse budgétaire
A5: Taux USD/MGA | B5: 4450 | C5: MGA/USD | D5: Hypothèse de change
A6: Taux JPY/MGA | B6: 30.5 | C6: MGA/JPY | D6: Hypothèse de change
A7: Augmentation salariale | B7: 0.07 | C7: % | D7: Hypothèse RH
A8: TVA | B8: 0.2 | C8: % | D8: Paramètre fiscal
A9: Site principal | B9: FORT DAUPHIN | D9: Administration / export
A10: Site production | B10: AMPANDRANDAVA | D10: Production
A12: MARCHES EXPORT
A13: Pays | B13: Entité représentatrice | C13: Devise | D13: Observation
A14: Japon | B14: GOODEIS | C14: JPY | D14: Relation export issue de la correction utilisateur
A15: Russie | B15: ELINAR | C15: USD | D15: Relation export issue de la correction utilisateur
A16: Chine | B16: REPRESENTANT CHINE - A VALIDER | C16: USD | D16: Nom exact à confirmer depuis Données SOMIDA

Sheet Employes
A1: Matricule | B1: Nom simulé | C1: Site | D1: Département | E1: Poste | F1: Salaire base mensuel (MGA) | G1: Prime mensuelle (MGA) | H1: Charges patronales (MGA) | I1: Coût mensuel total (MGA) | J1: Statut
A2: EMP-001 | B2: RABE Hery | C2: FORT DAUPHIN | D2: Direction | E2: Directeur Général | F2: 12440000 | G2: 1244000 | H2: 2239000 | I2: 15923000 | J2: Actif
A3: EMP-002 | B3: RAKOTO Miora | C3: AMPANDRANDAVA | D3: Direction | E3: DAF | F3: 9320000 | G3: 932000 | H3: 1678000 | I3: 11930000 | J3: Actif
A4: EMP-003 | B4: ANDRIA Fanja | C4: FORT DAUPHIN | D4: Finance | E4: Chef comptable | F4: 5310000 | G4: 637000 | H4: 956000 | I4: 6903000 | J4: Actif
A5: EMP-004 | B5: RAZAFY Toky | C5: FORT DAUPHIN | D5: Finance | E5: Comptable | F5: 3410000 | G5: 273000 | H5: 614000 | I5: 4297000 | J5: Actif
A6: EMP-005 | B6: RANDRIA Nirina | C6: AMPANDRANDAVA | D6: Finance | E6: Assistant comptable | F6: 2270000 | G6: 114000 | H6: 409000 | I6: 2793000 | J6: Actif
A7: EMP-006 | B7: RATSIM Lova | C7: AMPANDRANDAVA | D7: RH | E7: Responsable RH | F7: 4750000 | G7: 380000 | H7: 855000 | I7: 5985000 | J7: Actif
A8: EMP-007 | B8: RAJAO Aina | C8: AMPANDRANDAVA | D8: Commercial | E8: Responsable commercial export | F8: 5390000 | G8: 431000 | H8: 970000 | I8: 6791000 | J8: Actif
A9: EMP-008 | B9: RAMAN Tiana | C9: AMPANDRANDAVA | D9: Commercial | E9: Agent export | F9: 3070000 | G9: 154000 | H9: 553000 | I9: 3777000 | J9: Actif
A10: EMP-009 | B10: RAKOTON Zo | C10: FORT DAUPHIN | D10: Production | E10: Responsable production | F10: 5310000 | G10: 637000 | H10: 956000 | I10: 6903000 | J10: Actif
A11: EMP-010 | B11: RAZAN Mamy | C11: FORT DAUPHIN | D11: Production | E11: Chef d'atelier | F11: 3320000 | G11: 332000 | H11: 598000 | I11: 4250000 | J11: Actif
A12: EMP-011 | B12: RABE Hery | C12: FORT DAUPHIN | D12: Production | E12: Contrôleur qualité | F12: 2540000 | G12: 203000 | H12: 457000 | I12: 3200000 | J12: Actif
A13: EMP-012 | B13: RAKOTO Miora | C13: TRANOMARO | D13: Production | E13: Opérateur traitement | F13: 1680000 | G13: 134000 | H13: 302000 | I13: 2116000 | J13: Actif
... A61: EMP-060 | B61: RAZAN Mamy | C61: AMBOASARY | D61: RH | E61: Responsable RH | F61: 4300000 | G61: 516000 | H61: 774000 | I61: 5590000 | J61: Actif

Sheet Production
A1: Site | B1: Produit | C1: Unité | D1: Janvier | E1: Février | F1: Mars | G1: Avril | H1: Mai | I1: Juin | J1: Juillet | K1: Août | L1: Septembre | M1: Octobre | N1: Novembre | O1: Décembre | P1: Total annuel
A2: AMPANDRANDAVA | B2: ABR COUPE | C2: tonnes | D2: 82.32 | E2: 75.17 | F2: 65.38 | G2: 78.56 | H2: 64.5 | I2: 71.12 | J2: 82.55 | K2: 72.83 | L2: 63.98 | M2: 76.17 | N2: 81.22 | O2: 79.42 | P2: 893.22
A3: AMPANDRANDAVA | B3: FP1 COUPE | C3: tonnes | D3: 61.98 | E3: 51.81 | F3: 49.24 | G3: 56.27 | H3: 56.66 | I3: 50.8 | J3: 56.93 | K3: 54.42 | L3: 62.86 | M3: 58.95 | N3: 51.69 | O3: 56.52 | P3: 668.13
A4: AMPANDRANDAVA | B4: FP2 COUPE | C4: tonnes | D4: 52.28 | E4: 54.81 | F4: 48.69 | G4: 44.14 | H4: 48.99 | I4: 47.14 | J4: 49.53 | K4: 43.77 | L4: 50.56 | M4: 44.84 | N4: 54.51 | O4: 45.48 | P4: 584.74
A5: AMPANDRANDAVA | B5: TRA | C5: tonnes | D5: 70.69 | E5: 66.4 | F5: 63.68 | G5: 57.18 | H5: 62.68 | I5: 60.45 | J5: 64.67 | K5: 59.42 | L5: 70.84 | M5: 70.5 | N5: 59.4 | O5: 70.19 | P5: 776.1
A6: AMPANDRANDAVA | B6: BSA | C6: tonnes | D6: 43.34 | E6: 39.73 | F6: 44.63 | G6: 47.76 | H6: 42.02 | I6: 42.94 | J6: 39.3 | K6: 46.54 | L6: 38.76 | M6: 41.33 | N6: 37.82 | O6: 40.11 | P6: 504.28
A7: FORT DAUPHIN | B7: ABR COUPE | C7: tonnes | D7: 76.78 | E7: 79.32 | F7: 64.82 | G7: 63.93 | H7: 66.68 | I7: 75.04 | J7: 68.33 | K7: 75.91 | L7: 70.33 | M7: 68.01 | N7: 65.89 | O7: 81.17 | P7: 856.21
A8: FORT DAUPHIN | B8: FP1 COUPE | C8: tonnes | D8: 63.26 | E8: 60.62 | F8: 63.27 | G8: 57.16 | H8: 53.49 | I8: 48.36 | J8: 59.22 | K8: 49.51 | L8: 54.29 | M8: 52.64 | N8: 63.75 | O8: 63.07 | P8: 688.64
A9: FORT DAUPHIN | B9: FP2 COUPE | C9: tonnes | D9: 42.38 | E9: 49.61 | F9: 41.75 | G9: 50.5 | H9: 45.05 | I9: 53.5 | J9: 44.01 | K9: 53.57 | L9: 47.53 | M9: 44.05 | N9: 48.08 | O9: 45.11 | P9: 565.14
A10: FORT DAUPHIN | B10: TRA | C10: tonnes | D10: 63.91 | E10: 56.96 | F10: 60.18 | G10: 69.43 | H10: 70.08 | I10: 66.35 | J10: 67.42 | K10: 59.32 | L10: 66.25 | M10: 58.2 | N10: 67.52 | O10: 57.68 | P10: 763.3
A11: FORT DAUPHIN | B11: BSA | C11: tonnes | D11: 44.87 | E11: 46.3 | F11: 44.77 | G11: 48.42 | H11: 40.39 | I11: 40.26 | J11: 44.95 | K11: 43.01 | L11: 45.59 | M11: 36.37 | N11: 39.63 | O11: 37.88 | P11: 512.44

Sheet Charges
A1: Catégorie | B1: Nature | C1: Site | D1: Unité | E1: Janvier | F1: Février | G1: Mars | H1: Avril | I1: Mai | J1: Juin | K1: Juillet | L1: Août | M1: Septembre | N1: Octobre | O1: Novembre | P1: Décembre | Q1: Total annuel
A2: PRODUCTION | B2: Matières et consommables | C2: AMPANDRANDAVA | D2: MGA | E2: 137291000 | F2: 145941000 | G2: 160223000 | H2: 135503000 | I2: 160170000 | J2: 132384000 | K2: 143134000 | L2: 147255000 | M2: 132152000 | N2: 132332000 | O2: 152684000 | P2: 136764000 | Q2: 1715833000
A3: PRODUCTION | B3: Énergie / électricité | C3: AMPANDRANDAVA | D3: MGA | E3: 49896000 | F3: 50375000 | G3: 54047000 | H3: 48614000 | I3: 42644000 | J3: 44110000 | K3: 50795000 | L3: 47772000 | M3: 45734000 | N3: 52881000 | O3: 49219000 | P3: 53123000 | Q3: 589210000
A4: PRODUCTION | B4: Traitement mica | C4: AMPANDRANDAVA | D4: MGA | E4: 85413000 | F4: 86123000 | G4: 77975000 | H4: 80009000 | I4: 90557000 | J4: 85235000 | K4: 82475000 | L4: 79617000 | M4: 75401000 | N4: 82565000 | O4: 92098000 | P4: 83465000 | Q4: 1000933000
A5: PRODUCTION | B5: Maintenance équipements | C5: AMPANDRANDAVA | D5: MGA | E5: 29736000 | F5: 31677000 | G5: 30771000 | H5: 28214000 | I5: 34041000 | J5: 31545000 | K5: 30414000 | L5: 33422000 | M5: 28813000 | N5: 35179000 | O5: 33528000 | P5: 31860000 | Q5: 379200000
A6: PRODUCTION | B6: Emballages | C6: FORT DAUPHIN | D6: MGA | E6: 22382000 | F6: 24134000 | G6: 25616000 | H6: 22515000 | I6: 24945000 | J6: 23000000 | K6: 24197000 | L6: 22936000 | M6: 22880000 | N6: 21455000 | O6: 22386000 | P6: 25484000 | Q6: 281930000
A7: ADMINISTRATION | B7: Télécommunications / Internet | C7: FORT DAUPHIN | D7: MGA | E7: 8007000 | F7: 6967000 | G7: 8353000 | H7: 8113000 | I7: 7595000 | J7: 8445000 | K7: 6787000 | L7: 7506000 | M7: 7094000 | N7: 6701000 | O7: 6975000 | P7: 6850000 | Q7: 89393000
A8: ADMINISTRATION | B8: Assurances | C8: FORT DAUPHIN | D8: MGA | E8: 12621000 | F8: 12910000 | G8: 13878000 | H8: 14384000 | I8: 11846000 | J8: 14216000 | K8: 12903000 | L8: 11463000 | M8: 13629000 | N8: 14135000 | O8: 13133000 | P8: 13763000 | Q8: 158881000
A9: ADMINISTRATION | B9: Honoraires et conseil | C9: FORT DAUPHIN | D9: MGA | E9: 17180000 | F9: 14890000 | G9: 17423000 | H9: 16114000 | I9: 16798000 | J9: 17913000 | K9: 16061000 | L9: 15665000 | M9: 15891000 | N9: 14964000 | O9: 14257000 | P9: 16876000 | Q9: 194032000
A10: LOGISTIQUE | B10: Transport interne | C10: FORT DAUPHIN | D10: MGA | E10: 37704000 | F10: 39710000 | G10: 38432000 | H10: 34160000 | I10: 35986000 | J10: 41103000 | K10: 34551000 | L10: 39408000 | M10: 38527000 | N10: 36872000 | O10: 36549000 | P10: 40970000 | Q10: 453972000
A11: LOGISTIQUE | B11: Magasinage / manutention | C11: FORT DAUPHIN | D11: MGA | E11: 22710000 | F11: 21975000 | G11: 23472000 | H11: 23708000 | I11: 23782000 | J11: 20868000 | K11: 21599000 | L11: 23896000 | M11: 22113000 | N11: 20775000 | O11: 19975000 | P11: 20734000 | Q11: 265607000
A12: FISCAL | B12: Impôts et taxes | C12: FORT DAUPHIN | D12: MGA | E12: 27301000 | F12: 30019000 | G12: 28557000 | H12: 26655000 | I12: 28846000 | J12: 25035000 | K12: 29174000 | L12: 25582000 | M12: 24483000 | N12: 24858000 | O12: 25308000 | P12: 29799000 | Q12: 325617000
A13: FINANCE | B13: Frais bancaires | C13: FORT DAUPHIN | D13: MGA | E13: 10432000 | F13: 9889000 | G13: 12335000 | H13: 12000000 | I13: 10368000 | J13: 12156000 | K13: 12370000 | L13: 9908000 | M13: 10698000 | N13: 10148000 | O13: 10671000 | P13: 11836000 | Q13: 132811000
A14: SECURITE | B14: Gardiennage / sécurité | C14: AMPANDRANDAVA | D14: MGA | E14: 16231000 | F14: 15363000 | G14: 16047000 | H14: 14824000 | I14: 15529000 | J14: 14110000 | K14: 13335000 | L14: 16093000 | M14: 16062000 | N14: 14521000 | O14: 15250000 | P14: 14927000 | Q14: 182292000

Sheet Exportations
A1: SOMIDA — TABLEAU DE BORD DES EXPORTATIONS 2024
A2: Pilotage DAF • Japon / Russie / Chine • Suivi mensuel des volumes, devises et chiffre d’affaires
A4: VOLUME EXPORTÉ (t) | D4: CA EXPORT (MGA) | G4: CA JAPON (MGA) | J4: CA RUSSIE (MGA) | M4: CA CHINE (MGA) | P4: MARCHÉS / DEVISES
A5: =SUMIF($E$10:$E$54,"Quantité exportée",$S$10:$S$54) -> 3094.92 | D5: =SUMIF($E$10:$E$54,"Chiffre d'affaires MGA",$S$10:$S$54) -> 17737746840 | G5: =SUMIFS($S$10:$S$54,$A$10:$A$54,"Japon",$E$10:$E$54,"Chiffre d'affaires MGA") -> 5418113635 | J5: =SUMIFS($S$10:$S$54,$A$10:$A$54,"Russie",$E$10:$E$54,"Chiffre d'affaires MGA") -> 6201787445 | M5: =SUMIFS($S$10:$S$54,$A$10:$A$54,"Chine",$E$10:$E$54,"Chiffre d'affaires MGA") -> 6117845760 | P5: 3 pays • JPY / USD
A7: DÉTAIL MENSUEL DES EXPORTATIONS PAR MARCHÉ, REPRÉSENTANT ET PRODUIT
A9: Pays | B9: Entité représentatrice | C9: Produit | D9: Devise | E9: Indicateur | F9: Unité | G9: Janvier | H9: Février | I9: Mars | J9: Avril | K9: Mai | L9: Juin | M9: Juillet | N9: Août | O9: Septembre | P9: Octobre | Q9: Novembre | R9: Décembre | S9: Total annuel
A10: Japon | B10: GOODEIS | C10: ABR COUPE | D10: JPY | E10: Quantité exportée | F10: tonnes | G10: 26.98 | H10: 20.36 | I10: 16.55 | J10: 18.41 | K10: 16.68 | L10: 25.44 | M10: 21.5 | N10: 25.5 | O10: 16.9 | P10: 15.88 | Q10: 16.83 | R10: 25.95 | S10: 246.98
A11: Japon | B11: GOODEIS | C11: ABR COUPE | D11: JPY | E11: Chiffre d'affaires devise | F11: JPY | G11: 4991300 | H11: 3766600 | I11: 3061750 | J11: 3405850 | K11: 3085800 | L11: 4706400 | M11: 3977500 | N11: 4717500 | O11: 3126500 | P11: 2937800 | Q11: 3113550 | R11: 4800750 | S11: 45691300
A12: Japon | B12: GOODEIS | C12: ABR COUPE | D12: JPY | E12: Chiffre d'affaires MGA | F12: MGA | G12: 152234650 | H12: 114881300 | I12: 93383375 | J12: 103878425 | K12: 94116900 | L12: 143545200 | M12: 121313750 | N12: 143883750 | O12: 95358250 | P12: 89602900 | Q12: 94963275 | R12: 146422875 | S12: 1393584650
A13: Japon | B13: GOODEIS | C13: FP1 COUPE | D13: JPY | E13: Quantité exportée | F13: tonnes | G13: 18.23 | H13: 14.24 | I13: 18.92 | J13: 14.44 | K13: 20.13 | L13: 21.29 | M13: 17.77 | N13: 19.57 | O13: 16.22 | P13: 17.27 | Q13: 15.9 | R13: 14.77 | S13: 208.75
A14: Japon | B14: GOODEIS | C14: FP1 COUPE | D14: JPY | E14: Chiffre d'affaires devise | F14: JPY | G14: 3117330 | H14: 2435040 | I14: 3235320 | J14: 2469240 | K14: 3442230 | L14: 3640590 | M14: 3038670 | N14: 3346470 | O14: 2773620 | P14: 2953170 | Q14: 2718900 | R14: 2525670 | S14: 35696250
A15: Japon | B15: GOODEIS | C15: FP1 COUPE | D15: JPY | E15: Chiffre d'affaires MGA | F15: MGA | G15: 95078565 | H15: 74268720 | I15: 98677260 | J15: 75311820 | K15: 104988015 | L15: 111037995 | M15: 92679435 | N15: 102067335 | O15: 84595410 | P15: 90071685 | Q15: 82926450 | R15: 77032935 | S15: 1088735625
A16: Japon | B16: GOODEIS | C16: FP2 COUPE | D16: JPY | E16: Quantité exportée | F16: tonnes | G16: 17.69 | H16: 18.26 | I16: 16.81 | J16: 12.01 | K16: 13.83 | L16: 12.45 | M16: 14.83 | N16: 16.64 | O16: 19.18 | P16: 11.88 | Q16: 14.27 | R16: 18.46 | S16: 186.31
A17: Japon | B17: GOODEIS | C17: FP2 COUPE | D17: JPY | E17: Chiffre d'affaires devise | F17: JPY | G17: 2918850 | H17: 3012900 | I17: 2773650 | J17: 1981650 | K17: 2281950 | L17: 2054250 | M17: 2446950 | N17: 2745600 | O17: 3164700 | P17: 1960200 | Q17: 2354550 | R17: 3045900 | S17: 30741150
A18: Japon | B18: GOODEIS | C18: FP2 COUPE | D18: JPY | E18: Chiffre d'affaires MGA | F18: MGA | G18: 89024925 | H18: 91893450 | I18: 84596325 | J18: 60440325 | K18: 69599475 | L18: 62654625 | M18: 74631975 | N18: 83740800 | O18: 96523350 | P18: 59786100 | Q18: 71813775 | R18: 92899950 | S18: 937605075
A19: Japon | B19: GOODEIS | C19: TRA | D19: JPY | E19: Quantité exportée | F19: tonnes | G19: 17.08 | H19: 19.28 | I19: 23.69 | J19: 16.17 | K19: 18.62 | L19: 24.79 | M19: 21.53 | N19: 22.55 | O19: 20.48 | P19: 21.28 | Q19: 18.05 | R19: 21.47 | S19: 244.99
A20: Japon | B20: GOODEIS | C20: TRA | D20: JPY | E20: Chiffre d'affaires devise | F20: JPY | G20: 3040240 | H20: 3431840 | I20: 4216820 | J20: 2878260 | K20: 3314360 | L20: 4412620 | M20: 3832340 | N20: 4013900 | O20: 3645440 | P20: 3787840 | Q20: 3212900 | R20: 3821660 | S20: 43608220
A21: Japon | B21: GOODEIS | C21: TRA | D21: JPY | E21: Chiffre d'affaires MGA | F21: MGA | G21: 92727320 | H21: 104671120 | I21: 128613010 | J21: 87786930 | K21: 101087980 | L21: 134584910 | M21: 116886370 | N21: 122423950 | O21: 111185920 | P21: 115529120 | Q21: 97993450 | R21: 116560630 | S21: 1330050710
... A54: Chine | B54: REPRESENTANT CHINE - A VALIDER | C54: BSA | D54: USD | E54: Chiffre d'affaires MGA | F54: MGA | G54: 69103160 | H54: 53297650 | I54: 58181080 | J54: 72831370 | K54: 75614400 | L54: 59388810 | M54: 76034480 | N54: 71938700 | O54: 49989520 | P54: 68998140 | Q54: 47941630 | R54: 54085300 | S54: 757404240

Sheet Frais Export
A1: Pays | B1: Entité représentatrice | C1: Nature frais | D1: Unité | E1: Janvier | F1: Février | G1: Mars | H1: Avril | I1: Mai | J1: Juin | K1: Juillet | L1: Août | M1: Septembre | N1: Octobre | O1: Novembre | P1: Décembre | Q1: Total annuel
A2: Japon | B2: GOODEIS | C2: Transport local | D2: MGA | E2: 15459000 | F2: 13310000 | G2: 12505000 | H2: 14540000 | I2: 14596000 | J2: 14147000 | K2: 14864000 | L2: 13826000 | M2: 12952000 | N2: 16240000 | O2: 12290000 | P2: 12958000 | Q2: 167687000
A3: Japon | B3: GOODEIS | C3: Transit & documents | D3: MGA | E3: 6129000 | F3: 6722000 | G3: 7207000 | H3: 6738000 | I3: 5533000 | J3: 5968000 | K3: 6557000 | L3: 6476000 | M3: 6986000 | N3: 6522000 | O3: 7462000 | P3: 6749000 | Q3: 79049000
A4: Japon | B4: GOODEIS | C4: Manutention portuaire | D4: MGA | E4: 8498000 | F4: 9006000 | G4: 7622000 | H4: 9242000 | I4: 8370000 | J4: 8568000 | K4: 7737000 | L4: 8357000 | M4: 9697000 | N4: 9406000 | O4: 8223000 | P4: 9865000 | Q4: 104591000
A5: Japon | B5: GOODEIS | C5: Fret international | D5: MGA | E5: 44071000 | F5: 52068000 | G5: 51155000 | H5: 43594000 | I5: 50871000 | J5: 52049000 | K5: 47609000 | L5: 56141000 | M5: 42383000 | N5: 51569000 | O5: 52253000 | P5: 47695000 | Q5: 591458000
A6: Japon | B6: GOODEIS | C6: Assurance transport | D6: MGA | E6: 4098000 | F6: 5257000 | G6: 5277000 | H6: 5207000 | I6: 5287000 | J6: 4862000 | K6: 5230000 | L6: 5380000 | M6: 4330000 | N6: 4945000 | O6: 5318000 | P6: 4404000 | Q6: 59595000
A7: Japon | B7: GOODEIS | C7: Frais bancaires export | D7: MGA | E7: 3111000 | F7: 2815000 | G7: 3177000 | H7: 3226000 | I7: 3415000 | J7: 2822000 | K7: 2849000 | L7: 3707000 | M7: 3643000 | N7: 2862000 | O7: 2996000 | P7: 2996000 | Q7: 37619000
A8: Russie | B8: ELINAR | C8: Transport local | D8: MGA | E8: 14165000 | F8: 15237000 | G8: 15725000 | H8: 15379000 | I8: 13119000 | J8: 16977000 | K8: 13506000 | L8: 13582000 | M8: 16299000 | N8: 16760000 | O8: 17053000 | P8: 16623000 | Q8: 184425000
A9: Russie | B9: ELINAR | C9: Transit & documents | D9: MGA | E9: 7683000 | F9: 7264000 | G9: 7878000 | H9: 7601000 | I9: 7045000 | J9: 6064000 | K9: 6233000 | L9: 7190000 | M9: 7830000 | N9: 6135000 | O9: 6117000 | P9: 8063000 | Q9: 85103000
A10: Russie | B10: ELINAR | C10: Manutention portuaire | D10: MGA | E10: 8441000 | F10: 9389000 | G10: 10408000 | H10: 8389000 | I10: 8472000 | J10: 10564000 | K10: 10540000 | L10: 9393000 | M10: 10447000 | N10: 10370000 | O10: 10391000 | P10: 10992000 | Q10: 117796000
A11: Russie | B11: ELINAR | C11: Fret international | D11: MGA | E11: 46401000 | F11: 53435000 | G11: 61706000 | H11: 47465000 | I11: 51886000 | J11: 47977000 | K11: 57969000 | L11: 48532000 | M11: 55908000 | N11: 57871000 | O11: 48110000 | P11: 60561000 | Q11: 637821000
A12: Russie | B12: ELINAR | C12: Assurance transport | D12: MGA | E12: 4425000 | F12: 5120000 | G12: 4811000 | H12: 5460000 | I12: 5690000 | J12: 4904000 | K12: 4395000 | L12: 5218000 | M12: 5111000 | N12: 5614000 | O12: 5658000 | P12: 4373000 | Q12: 60779000
A13: Russie | B13: ELINAR | C13: Frais bancaires export | D13: MGA | E13: 3354000 | F13: 4022000 | G13: 3974000 | H13: 3440000 | I13: 3518000 | J13: 3182000 | K13: 3795000 | L13: 3610000 | M13: 3260000 | N13: 3474000 | O13: 3279000 | P13: 3852000 | Q13: 42760000
... A19: Chine | B19: REPRESENTANT CHINE - A VALIDER | C19: Frais bancaires export | D19: MGA | E19: 2956000 | F19: 3084000 | G19: 2711000 | H19: 2529000 | I19: 2501000 | J19: 2567000 | K19: 2562000 | L19: 3180000 | M19: 2525000 | N19: 2545000 | O19: 3020000 | P19: 3337000 | Q19: 33517000

Sheet Synthese
A1: Indicateur | B1: Unité | C1: Janvier | D1: Février | E1: Mars | F1: Avril | G1: Mai | H1: Juin | I1: Juillet | J1: Août | K1: Septembre | L1: Octobre | M1: Novembre | N1: Décembre | O1: Total annuel
A2: CA export | B2: MGA | C2: =SUMIF(Exportations!$E$2:$E$46,"Chiffre d'affaires MGA",Exportations!$G$2:$G$46) -> 1231654200 | D2: =SUMIF(Exportations!$E$2:$E$46,"Chiffre d'affaires MGA",Exportations!$H$2:$H$46) -> 1241735655 | E2: =SUMIF(Exportations!$E$2:$E$46,"Chiffre d'affaires MGA",Exportations!$I$2:$I$46) -> 1232355075 | F2: =SUMIF(Exportations!$E$2:$E$46,"Chiffre d'affaires MGA",Exportations!$J$2:$J$46) -> 1098155410 | G2: =SUMIF(Exportations!$E$2:$E$46,"Chiffre d'affaires MGA",Exportations!$K$2:$K$46) -> 1222025970 | H2: =SUMIF(Exportations!$E$2:$E$46,"Chiffre d'affaires MGA",Exportations!$L$2:$L$46) -> 1228057480 | I2: =SUMIF(Exportations!$E$2:$E$46,"Chiffre d'affaires MGA",Exportations!$M$2:$M$46) -> 1140252640 | J2: =SUMIF(Exportations!$E$2:$E$46,"Chiffre d'affaires MGA",Exportations!$N$2:$N$46) -> 1275120150 | K2: =SUMIF(Exportations!$E$2:$E$46,"Chiffre d'affaires MGA",Exportations!$O$2:$O$46) -> 1164413865 | L2: =SUMIF(Exportations!$E$2:$E$46,"Chiffre d'affaires MGA",Exportations!$P$2:$P$46) -> 1182499070 | M2: =SUMIF(Exportations!$E$2:$E$46,"Chiffre d'affaires MGA",Exportations!$Q$2:$Q$46) -> 1119988090 | N2: =SUMIF(Exportations!$E$2:$E$46,"Chiffre d'affaires MGA",Exportations!$R$2:$R$46) -> 1274120995 | O2: =SUM(C2:N2) -> 14410378600
A3: Charges exploitation | B3: MGA | C3: =SUM(Charges!$E$2:$E$14) -> 476904000 | D3: =SUM(Charges!$F$2:$F$14) -> 489973000 | E3: =SUM(Charges!$G$2:$G$14) -> 507129000 | F3: =SUM(Charges!$H$2:$H$14) -> 464813000 | G3: =SUM(Charges!$I$2:$I$14) -> 503107000 | H3: =SUM(Charges!$J$2:$J$14) -> 470120000 | I3: =SUM(Charges!$K$2:$K$14) -> 477795000 | J3: =SUM(Charges!$L$2:$L$14) -> 480523000 | K3: =SUM(Charges!$M$2:$M$14) -> 453477000 | L3: =SUM(Charges!$N$2:$N$14) -> 467386000 | M3: =SUM(Charges!$O$2:$O$14) -> 492033000 | N3: =SUM(Charges!$P$2:$P$14) -> 486451000 | O3: =SUM(C3:N3) -> 5769711000
A4: Frais export | B4: MGA | C4: =SUM('Frais Export'!$E$2:$E$19) -> 243053000 | D4: =SUM('Frais Export'!$F$2:$F$19) -> 262920000 | E4: =SUM('Frais Export'!$G$2:$G$19) -> 270811000 | F4: =SUM('Frais Export'!$H$2:$H$19) -> 242956000 | G4: =SUM('Frais Export'!$I$2:$I$19) -> 260255000 | H4: =SUM('Frais Export'!$J$2:$J$19) -> 257373000 | I4: =SUM('Frais Export'!$K$2:$K$19) -> 250912000 | J4: =SUM('Frais Export'!$L$2:$L$19) -> 263962000 | K4: =SUM('Frais Export'!$M$2:$M$19) -> 258815000 | L4: =SUM('Frais Export'!$N$2:$N$19) -> 269332000 | M4: =SUM('Frais Export'!$O$2:$O$19) -> 254047000 | N4: =SUM('Frais Export'!$P$2:$P$19) -> 269121000 | O4: =SUM(C4:N4) -> 3103557000
A5: Masse salariale | B5: MGA | C5: =SUM(Employes!$I$2:$I$61) -> 311533000 | D5: =SUM(Employes!$I$2:$I$61) -> 311533000 | E5: =SUM(Employes!$I$2:$I$61) -> 311533000 | F5: =SUM(Employes!$I$2:$I$61) -> 311533000 | G5: =SUM(Employes!$I$2:$I$61) -> 311533000 | H5: =SUM(Employes!$I$2:$I$61) -> 311533000 | I5: =SUM(Employes!$I$2:$I$61) -> 311533000 | J5: =SUM(Employes!$I$2:$I$61) -> 311533000 | ... N5: =SUM(Employes!$I$2:$I$61) -> 311533000 | O5: =SUM(C5:N5) -> 3738396000
A6: Résultat opérationnel | B6: MGA | C6: =C2-C3-C4-C5 -> 200164200 | D6: =D2-D3-D4-D5 -> 177309655 | E6: =E2-E3-E4-E5 -> 142882075 | F6: =F2-F3-F4-F5 -> 78853410 | G6: =G2-G3-G4-G5 -> 147130970 | H6: =H2-H3-H4-H5 -> 189031480 | I6: =I2-I3-I4-I5 -> 100012640 | J6: =J2-J3-J4-J5 -> 219102150 | ... N6: =N2-N3-N4-N5 -> 207015995 | O6: =SUM(C6:N6) -> 1798714600
A7: Marge opérationnelle | B7: % | C7: =IFERROR(C6/C2,0) -> 0.16251656 | D7: =IFERROR(D6/D2,0) -> 0.14279179 | E7: =IFERROR(E6/E2,0) -> 0.11594229 | F7: =IFERROR(F6/F2,0) -> 0.071805329 | G7: =IFERROR(G6/G2,0) -> 0.12039922 | H7: =IFERROR(H6/H2,0) -> 0.15392722 | I7: =IFERROR(I6/I2,0) -> 0.087710948 | J7: =IFERROR(J6/J2,0) -> 0.17182863 | ... O7: =IFERROR(O6/O2,0) -> 0.12482077
