Workbook

Sheet Donnees SOMIDA
A1: DONNEES SOMIDA - PARAMETRES ET REFERENTIELS
A2: Paramètre | B2: Valeur | C2: Unité / devise | D2: Commentaire
A3: Exercice | B3: 2021 | C3: année | D3: Exercice
A4: Inflation annuelle | B4: 0.058 | C4: % | D4: Paramètre annuel
A5: Taux USD/MGA | B5: 3990 | C5: MGA/USD | D5: Taux de change
A6: Taux JPY/MGA | B6: 36.4 | C6: MGA/JPY | D6: Taux de change
A7: Augmentation salariale | B7: 0.05 | C7: % | D7: Évolution salariale
A8: TVA | B8: 0.2 | C8: % | D8: Paramètre fiscal
A9: Site principal | B9: FORT DAUPHIN | D9: Administration / export
A10: Site production | B10: AMPANDRANDAVA | D10: Production
A12: MARCHES EXPORT
A13: Pays | B13: Entité représentatrice | C13: Devise | D13: Observation
A14: Japon | B14: GOODEIS | C14: JPY | D14: Marché export
A15: Russie | B15: ELINAR | C15: USD | D15: Marché export
A16: Chine | B16: REPRESENTANT CHINE | C16: USD | D16: Marché export

Sheet Employes
A1: Matricule | B1: Nom | C1: Site | D1: Département | E1: Poste | F1: Salaire base mensuel (MGA) | G1: Prime mensuelle (MGA) | H1: Charges patronales (MGA) | I1: Coût mensuel total (MGA) | J1: Statut
A2: EMP-001 | B2: RABE Hery | C2: FORT DAUPHIN | D2: Direction | E2: Directeur Général | F2: 11320400 | G2: 1132040 | H2: 2037490 | I2: =SUM(F2:H2) -> 14489930 | J2: Actif
A3: EMP-002 | B3: RAKOTO Miora | C3: AMPANDRANDAVA | D3: Direction | E3: DAF | F3: 8481200 | G3: 848120 | H3: 1526980 | I3: =SUM(F3:H3) -> 10856300 | J3: Actif
A4: EMP-003 | B4: ANDRIA Fanja | C4: FORT DAUPHIN | D4: Finance | E4: Chef comptable | F4: 4832100 | G4: 579670 | H4: 869960 | I4: =SUM(F4:H4) -> 6281730 | J4: Actif
A5: EMP-004 | B5: RAZAFY Toky | C5: FORT DAUPHIN | D5: Finance | E5: Comptable | F5: 3103100 | G5: 248430 | H5: 558740 | I5: =SUM(F5:H5) -> 3910270 | J5: Actif
A6: EMP-005 | B6: RANDRIA Nirina | C6: AMPANDRANDAVA | D6: Finance | E6: Assistant comptable | F6: 2065700 | G6: 103740 | H6: 372190 | I6: =SUM(F6:H6) -> 2541630 | J6: Actif
A7: EMP-006 | B7: RATSIM Lova | C7: AMPANDRANDAVA | D7: RH | E7: Responsable RH | F7: 4322500 | G7: 345800 | H7: 778050 | I7: =SUM(F7:H7) -> 5446350 | J7: Actif
A8: EMP-007 | B8: RAJAO Aina | C8: AMPANDRANDAVA | D8: Commercial | E8: Responsable commercial export | F8: 4904900 | G8: 392210 | H8: 882700 | I8: =SUM(F8:H8) -> 6179810 | J8: Actif
A9: EMP-008 | B9: RAMAN Tiana | C9: AMPANDRANDAVA | D9: Commercial | E9: Agent export | F9: 2793700 | G9: 140140 | H9: 503230 | I9: =SUM(F9:H9) -> 3437070 | J9: Actif
A10: EMP-009 | B10: RAKOTON Zo | C10: FORT DAUPHIN | D10: Production | E10: Responsable production | F10: 4832100 | G10: 579670 | H10: 869960 | I10: =SUM(F10:H10) -> 6281730 | J10: Actif
A11: EMP-010 | B11: RAZAN Mamy | C11: FORT DAUPHIN | D11: Production | E11: Chef d'atelier | F11: 3021200 | G11: 302120 | H11: 544180 | I11: =SUM(F11:H11) -> 3867500 | J11: Actif
A12: EMP-011 | B12: RABARY Lalaina | C12: FORT DAUPHIN | D12: Production | E12: Contrôleur qualité | F12: 2311400 | G12: 184730 | H12: 415870 | I12: =SUM(F12:H12) -> 2912000 | J12: Actif
A13: EMP-012 | B13: RAKOTOMALALA Tahina | C13: TRANOMARO | D13: Production | E13: Opérateur traitement | F13: 1528800 | G13: 121940 | H13: 274820 | I13: =SUM(F13:H13) -> 1925560 | J13: Actif
... A61: EMP-060 | B61: RAKOTOVONINA Rova | C61: AMBOASARY | D61: RH | E61: Responsable RH | F61: 3913000 | G61: 469560 | H61: 704340 | I61: =SUM(F61:H61) -> 5086900 | J61: Actif

Sheet Production
A1: Site | B1: Produit | C1: Unité | D1: Janvier | E1: Février | F1: Mars | G1: Avril | H1: Mai | I1: Juin | J1: Juillet | K1: Août | L1: Septembre | M1: Octobre | N1: Novembre | O1: Décembre | P1: Total annuel
A2: AMPANDRANDAVA | B2: ABR COUPE | C2: tonnes | D2: 74.09 | E2: 67.65 | F2: 58.84 | G2: 70.7 | H2: 58.05 | I2: 64.01 | J2: 74.3 | K2: 65.55 | L2: 57.58 | M2: 68.55 | N2: 73.1 | O2: 71.48 | P2: =SUM(D2:O2) -> 803.9
A3: AMPANDRANDAVA | B3: FP1 COUPE | C3: tonnes | D3: 55.78 | E3: 46.63 | F3: 44.32 | G3: 50.64 | H3: 50.99 | I3: 45.72 | J3: 51.24 | K3: 48.98 | L3: 56.57 | M3: 53.06 | N3: 46.52 | O3: 50.87 | P3: =SUM(D3:O3) -> 601.32
A4: AMPANDRANDAVA | B4: FP2 COUPE | C4: tonnes | D4: 47.05 | E4: 49.33 | F4: 43.82 | G4: 39.73 | H4: 44.09 | I4: 42.43 | J4: 44.58 | K4: 39.39 | L4: 45.5 | M4: 40.36 | N4: 49.06 | O4: 40.93 | P4: =SUM(D4:O4) -> 526.27
A5: AMPANDRANDAVA | B5: TRA | C5: tonnes | D5: 63.62 | E5: 59.76 | F5: 57.31 | G5: 51.46 | H5: 56.41 | I5: 54.41 | J5: 58.2 | K5: 53.48 | L5: 63.76 | M5: 63.45 | N5: 53.46 | O5: 63.17 | P5: =SUM(D5:O5) -> 698.49
A6: AMPANDRANDAVA | B6: BSA | C6: tonnes | D6: 39.01 | E6: 35.76 | F6: 40.17 | G6: 42.98 | H6: 37.82 | I6: 38.65 | J6: 35.37 | K6: 41.89 | L6: 34.88 | M6: 37.2 | N6: 34.04 | O6: 36.1 | P6: =SUM(D6:O6) -> 453.87
A7: FORT DAUPHIN | B7: ABR COUPE | C7: tonnes | D7: 69.1 | E7: 71.39 | F7: 58.34 | G7: 57.54 | H7: 60.01 | I7: 67.54 | J7: 61.5 | K7: 68.32 | L7: 63.3 | M7: 61.21 | N7: 59.3 | O7: 73.05 | P7: =SUM(D7:O7) -> 770.6
A8: FORT DAUPHIN | B8: FP1 COUPE | C8: tonnes | D8: 56.93 | E8: 54.56 | F8: 56.94 | G8: 51.44 | H8: 48.14 | I8: 43.52 | J8: 53.3 | K8: 44.56 | L8: 48.86 | M8: 47.38 | N8: 57.38 | O8: 56.76 | P8: =SUM(D8:O8) -> 619.77
A9: FORT DAUPHIN | B9: FP2 COUPE | C9: tonnes | D9: 38.14 | E9: 44.65 | F9: 37.58 | G9: 45.45 | H9: 40.55 | I9: 48.15 | J9: 39.61 | K9: 48.21 | L9: 42.78 | M9: 39.64 | N9: 43.27 | O9: 40.6 | P9: =SUM(D9:O9) -> 508.63
A10: FORT DAUPHIN | B10: TRA | C10: tonnes | D10: 57.52 | E10: 51.26 | F10: 54.16 | G10: 62.49 | H10: 63.07 | I10: 59.71 | J10: 60.68 | K10: 53.39 | L10: 59.62 | M10: 52.38 | N10: 60.77 | O10: 51.91 | P10: =SUM(D10:O10) -> 686.96
A11: FORT DAUPHIN | B11: BSA | C11: tonnes | D11: 40.38 | E11: 41.67 | F11: 40.29 | G11: 43.58 | H11: 36.35 | I11: 36.23 | J11: 40.46 | K11: 38.71 | L11: 41.03 | M11: 32.73 | N11: 35.67 | O11: 34.09 | P11: =SUM(D11:O11) -> 461.19

Sheet Charges
A1: Catégorie | B1: Nature | C1: Site | D1: Unité | E1: Janvier | F1: Février | G1: Mars | H1: Avril | I1: Mai | J1: Juin | K1: Juillet | L1: Août | M1: Septembre | N1: Octobre | O1: Novembre | P1: Décembre | Q1: Total annuel
A2: PRODUCTION | B2: Matières et consommables | C2: AMPANDRANDAVA | D2: MGA | E2: 120816080 | F2: 128428080 | G2: 140996240 | H2: 119242640 | I2: 140949600 | J2: 116497920 | K2: 125957920 | L2: 129584400 | M2: 116293760 | N2: 116452160 | O2: 134361920 | P2: 120352320 | Q2: 1509933040
A3: PRODUCTION | B3: Énergie / électricité | C3: AMPANDRANDAVA | D3: MGA | E3: 43908480 | F3: 44330000 | G3: 47561360 | H3: 42780320 | I3: 37526720 | J3: 38816800 | K3: 44699600 | L3: 42039360 | M3: 40245920 | N3: 46535280 | O3: 43312720 | P3: 46748240 | Q3: 518504800
A4: PRODUCTION | B4: Traitement mica | C4: AMPANDRANDAVA | D4: MGA | E4: 75163440 | F4: 75788240 | G4: 68618000 | H4: 70407920 | I4: 79690160 | J4: 75006800 | K4: 72578000 | L4: 70062960 | M4: 66352880 | N4: 72657200 | O4: 81046240 | P4: 73449200 | Q4: 880821040
A5: PRODUCTION | B5: Maintenance équipements | C5: AMPANDRANDAVA | D5: MGA | E5: 26167680 | F5: 27875760 | G5: 27078480 | H5: 24828320 | I5: 29956080 | J5: 27759600 | K5: 26764320 | L5: 29411360 | M5: 25355440 | N5: 30957520 | O5: 29504640 | P5: 28036800 | Q5: 333696000
A6: PRODUCTION | B6: Emballages | C6: FORT DAUPHIN | D6: MGA | E6: 19696160 | F6: 21237920 | G6: 22542080 | H6: 19813200 | I6: 21951600 | J6: 20240000 | K6: 21293360 | L6: 20183680 | M6: 20134400 | N6: 18880400 | O6: 19699680 | P6: 22425920 | Q6: 248098400
A7: ADMINISTRATION | B7: Salaires administratifs | C7: FORT DAUPHIN | D7: MGA | E7: 59750240 | F7: 56341120 | G7: 62360320 | H7: 57353120 | I7: 57582800 | J7: 54754480 | K7: 60673360 | L7: 60727920 | M7: 57833600 | N7: 54917280 | O7: 57889040 | P7: 61948480 | Q7: 702131760
A8: ADMINISTRATION | B8: Télécommunications / Internet | C8: FORT DAUPHIN | D8: MGA | E8: 7046160 | F8: 6130960 | G8: 7350640 | H8: 7139440 | I8: 6683600 | J8: 7431600 | K8: 5972560 | L8: 6605280 | M8: 6242720 | N8: 5896880 | O8: 6138000 | P8: 6028000 | Q8: 78665840
A9: ADMINISTRATION | B9: Assurances | C9: FORT DAUPHIN | D9: MGA | E9: 11106480 | F9: 11360800 | G9: 12212640 | H9: 12657920 | I9: 10424480 | J9: 12510080 | K9: 11354640 | L9: 10087440 | M9: 11993520 | N9: 12438800 | O9: 11557040 | P9: 12111440 | Q9: 139815280
A10: ADMINISTRATION | B10: Honoraires et conseil | C10: FORT DAUPHIN | D10: MGA | E10: 15118400 | F10: 13103200 | G10: 15332240 | H10: 14180320 | I10: 14782240 | J10: 15763440 | K10: 14133680 | L10: 13785200 | M10: 13984080 | N10: 13168320 | O10: 12546160 | P10: 14850880 | Q10: 170748160
A11: LOGISTIQUE | B11: Transport interne | C11: FORT DAUPHIN | D11: MGA | E11: 33179520 | F11: 34944800 | G11: 33820160 | H11: 30060800 | I11: 31667680 | J11: 36170640 | K11: 30404880 | L11: 34679040 | M11: 33903760 | N11: 32447360 | O11: 32163120 | P11: 36053600 | Q11: 399495360
A12: LOGISTIQUE | B12: Magasinage / manutention | C12: FORT DAUPHIN | D12: MGA | E12: 19984800 | F12: 19338000 | G12: 20655360 | H12: 20863040 | I12: 20928160 | J12: 18363840 | K12: 19007120 | L12: 21028480 | M12: 19459440 | N12: 18282000 | O12: 17578000 | P12: 18245920 | Q12: 233734160
A13: FISCAL | B13: Impôts et taxes | C13: FORT DAUPHIN | D13: MGA | E13: 24024880 | F13: 26416720 | G13: 25130160 | H13: 23456400 | I13: 25384480 | J13: 22030800 | K13: 25673120 | L13: 22512160 | M13: 21545040 | N13: 21875040 | O13: 22271040 | P13: 26223120 | Q13: 286542960
... A15: SECURITE | B15: Gardiennage / sécurité | C15: AMPANDRANDAVA | D15: MGA | E15: 14283280 | F15: 13519440 | G15: 14121360 | H15: 13045120 | I15: 13665520 | J15: 12416800 | K15: 11734800 | L15: 14161840 | M15: 14134560 | N15: 12778480 | O15: 13420000 | P15: 13135760 | Q15: 160416960

Sheet Exportations
A1: SOMIDA — TABLEAU DE BORD DES EXPORTATIONS 2021
A2: Pilotage DAF • Japon / Russie / Chine • Suivi mensuel des volumes, devises et chiffre d’affaires
A4: VOLUME EXPORTÉ (t) | D4: CA EXPORT (MGA) | G4: CA JAPON (MGA) | J4: CA RUSSIE (MGA) | M4: CA CHINE (MGA) | P4: MARCHÉS / DEVISES
A5: =SUMIF($E$10:$E$54,"Quantité exportée",$S$10:$S$54) -> 3094.92 | D5: =SUMIF($E$10:$E$54,"Chiffre d'affaires MGA",$S$10:$S$54) -> 17737746840 | G5: =SUMIFS($S$10:$S$54,$A$10:$A$54,"Japon",$E$10:$E$54,"Chiffre d'affaires MGA") -> 5418113635 | J5: =SUMIFS($S$10:$S$54,$A$10:$A$54,"Russie",$E$10:$E$54,"Chiffre d'affaires MGA") -> 6201787445 | M5: =SUMIFS($S$10:$S$54,$A$10:$A$54,"Chine",$E$10:$E$54,"Chiffre d'affaires MGA") -> 6117845760 | P5: 3 pays • JPY / USD
A7: DÉTAIL MENSUEL DES EXPORTATIONS PAR MARCHÉ, REPRÉSENTANT ET PRODUIT
A9: Pays | B9: Entité représentatrice | C9: Produit | D9: Devise | E9: Indicateur | F9: Unité | G9: Janvier | H9: Février | I9: Mars | J9: Avril | K9: Mai | L9: Juin | M9: Juillet | N9: Août | O9: Septembre | P9: Octobre | Q9: Novembre | R9: Décembre | S9: Total annuel
A10: Japon | B10: GOODEIS | C10: ABR COUPE | D10: JPY | E10: Quantité exportée | F10: tonnes | G10: 26.98 | H10: 20.36 | I10: 16.55 | J10: 18.41 | K10: 16.68 | L10: 25.44 | M10: 21.5 | N10: 25.5 | O10: 16.9 | P10: 15.88 | Q10: 16.83 | R10: 25.95 | S10: 246.98
A11: Japon | B11: GOODEIS | C11: ABR COUPE | D11: JPY | E11: Chiffre d'affaires devise | F11: JPY | G11: 4991300 | H11: 3766600 | I11: 3061750 | J11: 3405850 | K11: 3085800 | L11: 4706400 | M11: 3977500 | N11: 4717500 | O11: 3126500 | P11: 2937800 | Q11: 3113550 | R11: 4800750 | S11: 45691300
A12: Japon | B12: GOODEIS | C12: ABR COUPE | D12: JPY | E12: Chiffre d'affaires MGA | F12: MGA | G12: 152234650 | H12: 114881300 | I12: 93383375 | J12: 103878425 | K12: 94116900 | L12: 143545200 | M12: 121313750 | N12: 143883750 | O12: 95358250 | P12: 89602900 | Q12: 94963275 | R12: 146422875 | S12: 1393584650
A13: Japon | B13: GOODEIS | C13: FP1 COUPE | D13: JPY | E13: Quantité exportée | F13: tonnes | G13: 18.23 | H13: 14.24 | I13: 18.92 | J13: 14.44 | K13: 20.13 | L13: 21.29 | M13: 17.77 | N13: 19.57 | O13: 16.22 | P13: 17.27 | Q13: 15.9 | R13: 14.77 | S13: 208.75
A14: Japon | B14: GOODEIS | C14: FP1 COUPE | D14: JPY | E14: Chiffre d'affaires devise | F14: JPY | G14: 3117330 | H14: 2435040 | I14: 3235320 | J14: 2469240 | K14: 3442230 | L14: 3640590 | M14: 3038670 | N14: 3346470 | O14: 2773620 | P14: 2953170 | Q14: 2718900 | R14: 2525670 | S14: 35696250
A15: Japon | B15: GOODEIS | C15: FP1 COUPE | D15: JPY | E15: Chiffre d'affaires MGA | F15: MGA | G15: 95078565 | H15: 74268720 | I15: 98677260 | J15: 75311820 | K15: 104988015 | L15: 111037995 | M15: 92679435 | N15: 102067335 | O15: 84595410 | P15: 90071685 | Q15: 82926450 | R15: 77032935 | S15: 1088735625
A16: Japon | B16: GOODEIS | C16: FP2 COUPE | D16: JPY | E16: Quantité exportée | F16: tonnes | G16: 17.69 | H16: 18.26 | I16: 16.81 | J16: 12.01 | K16: 13.83 | L16: 12.45 | M16: 14.83 | N16: 16.64 | O16: 19.18 | P16: 11.88 | Q16: 14.27 | R16: 18.46 | S16: 186.31
A17: Japon | B17: GOODEIS | C17: FP2 COUPE | D17: JPY | E17: Chiffre d'affaires devise | F17: JPY | G17: 2918850 | H17: 3012900 | I17: 2773650 | J17: 1981650 | K17: 2281950 | L17: 2054250 | M17: 2446950 | N17: 2745600 | O17: 3164700 | P17: 1960200 | Q17: 2354550 | R17: 3045900 | S17: 30741150
A18: Japon | B18: GOODEIS | C18: FP2 COUPE | D18: JPY | E18: Chiffre d'affaires MGA | F18: MGA | G18: 89024925 | H18: 91893450 | I18: 84596325 | J18: 60440325 | K18: 69599475 | L18: 62654625 | M18: 74631975 | N18: 83740800 | O18: 96523350 | P18: 59786100 | Q18: 71813775 | R18: 92899950 | S18: 937605075
A19: Japon | B19: GOODEIS | C19: TRA | D19: JPY | E19: Quantité exportée | F19: tonnes | G19: 17.08 | H19: 19.28 | I19: 23.69 | J19: 16.17 | K19: 18.62 | L19: 24.79 | M19: 21.53 | N19: 22.55 | O19: 20.48 | P19: 21.28 | Q19: 18.05 | R19: 21.47 | S19: 244.99
A20: Japon | B20: GOODEIS | C20: TRA | D20: JPY | E20: Chiffre d'affaires devise | F20: JPY | G20: 3040240 | H20: 3431840 | I20: 4216820 | J20: 2878260 | K20: 3314360 | L20: 4412620 | M20: 3832340 | N20: 4013900 | O20: 3645440 | P20: 3787840 | Q20: 3212900 | R20: 3821660 | S20: 43608220
A21: Japon | B21: GOODEIS | C21: TRA | D21: JPY | E21: Chiffre d'affaires MGA | F21: MGA | G21: 92727320 | H21: 104671120 | I21: 128613010 | J21: 87786930 | K21: 101087980 | L21: 134584910 | M21: 116886370 | N21: 122423950 | O21: 111185920 | P21: 115529120 | Q21: 97993450 | R21: 116560630 | S21: 1330050710
... A54: Chine | B54: REPRESENTANT CHINE - A VALIDER | C54: BSA | D54: USD | E54: Chiffre d'affaires MGA | F54: MGA | G54: 69103160 | H54: 53297650 | I54: 58181080 | J54: 72831370 | K54: 75614400 | L54: 59388810 | M54: 76034480 | N54: 71938700 | O54: 49989520 | P54: 68998140 | Q54: 47941630 | R54: 54085300 | S54: 757404240

Sheet Frais Export
A1: Pays | B1: Entité représentatrice | C1: Nature frais | D1: Unité | E1: Janvier | F1: Février | G1: Mars | H1: Avril | I1: Mai | J1: Juin | K1: Juillet | L1: Août | M1: Septembre | N1: Octobre | O1: Novembre | P1: Décembre | Q1: Total annuel
A2: Japon | B2: GOODEIS | C2: Transport local | D2: MGA | E2: 12243528 | F2: 10541520 | G2: 9903960 | H2: 11515680 | I2: 11560032 | J2: 11204424 | K2: 11772288 | L2: 10950192 | M2: 10257984 | N2: 12862080 | O2: 9733680 | P2: 10262736 | Q2: =SUM(E2:P2) -> 132808104
A3: Japon | B3: GOODEIS | C3: Transit & documents | D3: MGA | E3: 4854168 | F3: 5323824 | G3: 5707944 | H3: 5336496 | I3: 4382136 | J3: 4726656 | K3: 5193144 | L3: 5128992 | M3: 5532912 | N3: 5165424 | O3: 5909904 | P3: 5345208 | Q3: =SUM(E3:P3) -> 62606808
A4: Japon | B4: GOODEIS | C4: Manutention portuaire | D4: MGA | E4: 6730416 | F4: 7132752 | G4: 6036624 | H4: 7319664 | I4: 6629040 | J4: 6785856 | K4: 6127704 | L4: 6618744 | M4: 7680024 | N4: 7449552 | O4: 6512616 | P4: 7813080 | Q4: =SUM(E4:P4) -> 82836072
A5: Japon | B5: GOODEIS | C5: Fret international | D5: MGA | E5: 34904232 | F5: 41237856 | G5: 40514760 | H5: 34526448 | I5: 40289832 | J5: 41222808 | K5: 37706328 | L5: 44463672 | M5: 33567336 | N5: 40842648 | O5: 41384376 | P5: 37774440 | Q5: =SUM(E5:P5) -> 468434736
A6: Japon | B6: GOODEIS | C6: Assurance transport | D6: MGA | E6: 3245616 | F6: 4163544 | G6: 4179384 | H6: 4123944 | I6: 4187304 | J6: 3850704 | K6: 4142160 | L6: 4260960 | M6: 3429360 | N6: 3916440 | O6: 4211856 | P6: 3487968 | Q6: =SUM(E6:P6) -> 47199240
A7: Japon | B7: GOODEIS | C7: Frais bancaires export | D7: MGA | E7: 2463912 | F7: 2229480 | G7: 2516184 | H7: 2554992 | I7: 2704680 | J7: 2235024 | K7: 2256408 | L7: 2935944 | M7: 2885256 | N7: 2266704 | O7: 2372832 | P7: 2372832 | Q7: =SUM(E7:P7) -> 29794248
A8: Russie | B8: ELINAR | C8: Transport local | D8: MGA | E8: 11218680 | F8: 12067704 | G8: 12454200 | H8: 12180168 | I8: 10390248 | J8: 13445784 | K8: 10696752 | L8: 10756944 | M8: 12908808 | N8: 13273920 | O8: 13505976 | P8: 13165416 | Q8: =SUM(E8:P8) -> 146064600
A9: Russie | B9: ELINAR | C9: Transit & documents | D9: MGA | E9: 6084936 | F9: 5753088 | G9: 6239376 | H9: 6019992 | I9: 5579640 | J9: 4802688 | K9: 4936536 | L9: 5694480 | M9: 6201360 | N9: 4858920 | O9: 4844664 | P9: 6385896 | Q9: =SUM(E9:P9) -> 67401576
A10: Russie | B10: ELINAR | C10: Manutention portuaire | D10: MGA | E10: 6685272 | F10: 7436088 | G10: 8243136 | H10: 6644088 | I10: 6709824 | J10: 8366688 | K10: 8347680 | L10: 7439256 | M10: 8274024 | N10: 8213040 | O10: 8229672 | P10: 8705664 | Q10: =SUM(E10:P10) -> 93294432
A11: Russie | B11: ELINAR | C11: Fret international | D11: MGA | E11: 36749592 | F11: 42320520 | G11: 48871152 | H11: 37592280 | I11: 41093712 | J11: 37997784 | K11: 45911448 | L11: 38437344 | M11: 44279136 | N11: 45833832 | O11: 38103120 | P11: 47964312 | Q11: =SUM(E11:P11) -> 505154232
A12: Russie | B12: ELINAR | C12: Assurance transport | D12: MGA | E12: 3504600 | F12: 4055040 | G12: 3810312 | H12: 4324320 | I12: 4506480 | J12: 3883968 | K12: 3480840 | L12: 4132656 | M12: 4047912 | N12: 4446288 | O12: 4481136 | P12: 3463416 | Q12: =SUM(E12:P12) -> 48136968
A13: Russie | B13: ELINAR | C13: Frais bancaires export | D13: MGA | E13: 2656368 | F13: 3185424 | G13: 3147408 | H13: 2724480 | I13: 2786256 | J13: 2520144 | K13: 3005640 | L13: 2859120 | M13: 2581920 | N13: 2751408 | O13: 2596968 | P13: 3050784 | Q13: =SUM(E13:P13) -> 33865920
... A19: Chine | B19: REPRESENTANT CHINE | C19: Frais bancaires export | D19: MGA | E19: 2341152 | F19: 2442528 | G19: 2147112 | H19: 2002968 | I19: 1980792 | J19: 2033064 | K19: 2029104 | L19: 2518560 | M19: 1999800 | N19: 2015640 | O19: 2391840 | P19: 2642904 | Q19: =SUM(E19:P19) -> 26545464

Sheet Synthese
A1: Indicateur | B1: Unité | C1: Janvier | D1: Février | E1: Mars | F1: Avril | G1: Mai | H1: Juin | I1: Juillet | J1: Août | K1: Septembre | L1: Octobre | M1: Novembre | N1: Décembre | O1: Total annuel
A2: CA export | B2: MGA | C2: =SUMIF(Exportations!$E$10:$E$80,"Chiffre d'affaires MGA",Exportations!$G$10:$G$80) -> 1543024260 | D2: =SUMIF(Exportations!$E$10:$E$80,"Chiffre d'affaires MGA",Exportations!$H$10:$H$80) -> 1544169225 | E2: =SUMIF(Exportations!$E$10:$E$80,"Chiffre d'affaires MGA",Exportations!$I$10:$I$80) -> 1521790195 | F2: =SUMIF(Exportations!$E$10:$E$80,"Chiffre d'affaires MGA",Exportations!$J$10:$J$80) -> 1368635310 | G2: =SUMIF(Exportations!$E$10:$E$80,"Chiffre d'affaires MGA",Exportations!$K$10:$K$80) -> 1498616165 | H2: =SUMIF(Exportations!$E$10:$E$80,"Chiffre d'affaires MGA",Exportations!$L$10:$L$80) -> 1475664825 | I2: =SUMIF(Exportations!$E$10:$E$80,"Chiffre d'affaires MGA",Exportations!$M$10:$M$80) -> 1470114230 | J2: =SUMIF(Exportations!$E$10:$E$80,"Chiffre d'affaires MGA",Exportations!$N$10:$N$80) -> 1547565170 | K2: =SUMIF(Exportations!$E$10:$E$80,"Chiffre d'affaires MGA",Exportations!$O$10:$O$80) -> 1402795470 | L2: =SUMIF(Exportations!$E$10:$E$80,"Chiffre d'affaires MGA",Exportations!$P$10:$P$80) -> 1507107880 | M2: =SUMIF(Exportations!$E$10:$E$80,"Chiffre d'affaires MGA",Exportations!$Q$10:$Q$80) -> 1328053180 | N2: =SUMIF(Exportations!$E$10:$E$80,"Chiffre d'affaires MGA",Exportations!$R$10:$R$80) -> 1530210930 | O2: =SUM(C2:N2) -> 17737746840
A3: Charges exploitation | B3: MGA | C3: =SUMIF(Charges!$A$2:$A$27,"PRODUCTION",Charges!$E$2:$E$27)+SUMIF(Charges!$A$2:$A$27,"ADMINISTRATION",Charges!$E$2:$E$27)-SUMIF(Charges!$B$2:$B$27,"Salaires administratifs",Charges!$E$2:$E$27)+SUMIF(Charges!$A$2:$A$27,"LOGISTIQUE",Charges!$E$2:$E$27)+SUMIF(Charges!$A$2:$A$27,"SECURITE",Charges!$E$2:$E$27)+SUMIF(Charges!$A$2:$A$27,"FISCAL",Charges!$E$2:$E$27)+C5+Charges!E27 -> 693990390 | D3: =SUMIF(Charges!$A$2:$A$27,"PRODUCTION",Charges!$F$2:$F$27)+SUMIF(Charges!$A$2:$A$27,"ADMINISTRATION",Charges!$F$2:$F$27)-SUMIF(Charges!$B$2:$B$27,"Salaires administratifs",Charges!$F$2:$F$27)+SUMIF(Charges!$A$2:$A$27,"LOGISTIQUE",Charges!$F$2:$F$27)+SUMIF(Charges!$A$2:$A$27,"SECURITE",Charges!$F$2:$F$27)+SUMIF(Charges!$A$2:$A$27,"FISCAL",Charges!$F$2:$F$27)+D5+Charges!F27 -> 705968950 | E3: =SUMIF(Charges!$A$2:$A$27,"PRODUCTION",Charges!$G$2:$G$27)+SUMIF(Charges!$A$2:$A$27,"ADMINISTRATION",Charges!$G$2:$G$27)-SUMIF(Charges!$B$2:$B$27,"Salaires administratifs",Charges!$G$2:$G$27)+SUMIF(Charges!$A$2:$A$27,"LOGISTIQUE",Charges!$G$2:$G$27)+SUMIF(Charges!$A$2:$A$27,"SECURITE",Charges!$G$2:$G$27)+SUMIF(Charges!$A$2:$A$27,"FISCAL",Charges!$G$2:$G$27)+E5+Charges!G27 -> 718913750 | F3: =SUMIF(Charges!$A$2:$A$27,"PRODUCTION",Charges!$H$2:$H$27)+SUMIF(Charges!$A$2:$A$27,"ADMINISTRATION",Charges!$H$2:$H$27)-SUMIF(Charges!$B$2:$B$27,"Salaires administratifs",Charges!$H$2:$H$27)+SUMIF(Charges!$A$2:$A$27,"LOGISTIQUE",Charges!$H$2:$H$27)+SUMIF(Charges!$A$2:$A$27,"SECURITE",Charges!$H$2:$H$27)+SUMIF(Charges!$A$2:$A$27,"FISCAL",Charges!$H$2:$H$27)+F5+Charges!H27 -> 681970470 | G3: =SUMIF(Charges!$A$2:$A$27,"PRODUCTION",Charges!$I$2:$I$27)+SUMIF(Charges!$A$2:$A$27,"ADMINISTRATION",Charges!$I$2:$I$27)-SUMIF(Charges!$B$2:$B$27,"Salaires administratifs",Charges!$I$2:$I$27)+SUMIF(Charges!$A$2:$A$27,"LOGISTIQUE",Charges!$I$2:$I$27)+SUMIF(Charges!$A$2:$A$27,"SECURITE",Charges!$I$2:$I$27)+SUMIF(Charges!$A$2:$A$27,"FISCAL",Charges!$I$2:$I$27)+G5+Charges!I27 -> 717105350 | H3: =SUMIF(Charges!$A$2:$A$27,"PRODUCTION",Charges!$J$2:$J$27)+SUMIF(Charges!$A$2:$A$27,"ADMINISTRATION",Charges!$J$2:$J$27)-SUMIF(Charges!$B$2:$B$27,"Salaires administratifs",Charges!$J$2:$J$27)+SUMIF(Charges!$A$2:$A$27,"LOGISTIQUE",Charges!$J$2:$J$27)+SUMIF(Charges!$A$2:$A$27,"SECURITE",Charges!$J$2:$J$27)+SUMIF(Charges!$A$2:$A$27,"FISCAL",Charges!$J$2:$J$27)+H5+Charges!J27 -> 686503350 | I3: =SUMIF(Charges!$A$2:$A$27,"PRODUCTION",Charges!$K$2:$K$27)+SUMIF(Charges!$A$2:$A$27,"ADMINISTRATION",Charges!$K$2:$K$27)-SUMIF(Charges!$B$2:$B$27,"Salaires administratifs",Charges!$K$2:$K$27)+SUMIF(Charges!$A$2:$A$27,"LOGISTIQUE",Charges!$K$2:$K$27)+SUMIF(Charges!$A$2:$A$27,"SECURITE",Charges!$K$2:$K$27)+SUMIF(Charges!$A$2:$A$27,"FISCAL",Charges!$K$2:$K$27)+I5+Charges!K27 -> 693069030 | J3: =SUMIF(Charges!$A$2:$A$27,"PRODUCTION",Charges!$L$2:$L$27)+SUMIF(Charges!$A$2:$A$27,"ADMINISTRATION",Charges!$L$2:$L$27)-SUMIF(Charges!$B$2:$B$27,"Salaires administratifs",Charges!$L$2:$L$27)+SUMIF(Charges!$A$2:$A$27,"LOGISTIQUE",Charges!$L$2:$L$27)+SUMIF(Charges!$A$2:$A$27,"SECURITE",Charges!$L$2:$L$27)+SUMIF(Charges!$A$2:$A$27,"FISCAL",Charges!$L$2:$L$27)+J5+Charges!L27 -> 697636230 | K3: =SUMIF(Charges!$A$2:$A$27,"PRODUCTION",Charges!$M$2:$M$27)+SUMIF(Charges!$A$2:$A$27,"ADMINISTRATION",Charges!$M$2:$M$27)-SUMIF(Charges!$B$2:$B$27,"Salaires administratifs",Charges!$M$2:$M$27)+SUMIF(Charges!$A$2:$A$27,"LOGISTIQUE",Charges!$M$2:$M$27)+SUMIF(Charges!$A$2:$A$27,"SECURITE",Charges!$M$2:$M$27)+SUMIF(Charges!$A$2:$A$27,"FISCAL",Charges!$M$2:$M$27)+K5+Charges!M27 -> 673140550 | L3: =SUMIF(Charges!$A$2:$A$27,"PRODUCTION",Charges!$N$2:$N$27)+SUMIF(Charges!$A$2:$A$27,"ADMINISTRATION",Charges!$N$2:$N$27)-SUMIF(Charges!$B$2:$B$27,"Salaires administratifs",Charges!$N$2:$N$27)+SUMIF(Charges!$A$2:$A$27,"LOGISTIQUE",Charges!$N$2:$N$27)+SUMIF(Charges!$A$2:$A$27,"SECURITE",Charges!$N$2:$N$27)+SUMIF(Charges!$A$2:$A$27,"FISCAL",Charges!$N$2:$N$27)+L5+Charges!N27 -> 685864470 | M3: =SUMIF(Charges!$A$2:$A$27,"PRODUCTION",Charges!$O$2:$O$27)+SUMIF(Charges!$A$2:$A$27,"ADMINISTRATION",Charges!$O$2:$O$27)-SUMIF(Charges!$B$2:$B$27,"Salaires administratifs",Charges!$O$2:$O$27)+SUMIF(Charges!$A$2:$A$27,"LOGISTIQUE",Charges!$O$2:$O$27)+SUMIF(Charges!$A$2:$A$27,"SECURITE",Charges!$O$2:$O$27)+SUMIF(Charges!$A$2:$A$27,"FISCAL",Charges!$O$2:$O$27)+M5+Charges!O27 -> 707093590 | N3: =SUMIF(Charges!$A$2:$A$27,"PRODUCTION",Charges!$P$2:$P$27)+SUMIF(Charges!$A$2:$A$27,"ADMINISTRATION",Charges!$P$2:$P$27)-SUMIF(Charges!$B$2:$B$27,"Salaires administratifs",Charges!$P$2:$P$27)+SUMIF(Charges!$A$2:$A$27,"LOGISTIQUE",Charges!$P$2:$P$27)+SUMIF(Charges!$A$2:$A$27,"SECURITE",Charges!$P$2:$P$27)+SUMIF(Charges!$A$2:$A$27,"FISCAL",Charges!$P$2:$P$27)+N5+Charges!P27 -> 701156230 | O3: =SUM(C3:N3) -> 8362412360
A4: Frais export | B4: MGA | C4: =SUM('Frais Export'!E2:E50) -> 192497976 | D4: =SUM('Frais Export'!F2:F50) -> 208232640 | E4: =SUM('Frais Export'!G2:G50) -> 214482312 | F4: =SUM('Frais Export'!H2:H50) -> 192421152 | G4: =SUM('Frais Export'!I2:I50) -> 206121960 | H4: =SUM('Frais Export'!J2:J50) -> 203839416 | I4: =SUM('Frais Export'!K2:K50) -> 198722304 | J4: =SUM('Frais Export'!L2:L50) -> 209057904 | ... N4: =SUM('Frais Export'!P2:P50) -> 213143832 | O4: =SUM(C4:N4) -> 2458017144
A5: Masse salariale | B5: MGA | C5: =SUM(Employes!$I$2:$I$100) -> 283495030 | D5: =SUM(Employes!$I$2:$I$100) -> 283495030 | E5: =SUM(Employes!$I$2:$I$100) -> 283495030 | F5: =SUM(Employes!$I$2:$I$100) -> 283495030 | G5: =SUM(Employes!$I$2:$I$100) -> 283495030 | H5: =SUM(Employes!$I$2:$I$100) -> 283495030 | I5: =SUM(Employes!$I$2:$I$100) -> 283495030 | J5: =SUM(Employes!$I$2:$I$100) -> 283495030 | ... N5: =SUM(Employes!$I$2:$I$100) -> 283495030 | O5: =SUM(C5:N5) -> 3401940360
A6: Résultat opérationnel | B6: MGA | C6: =C2-C3-C4 -> 656535894 | D6: =D2-D3-D4 -> 629967635 | E6: =E2-E3-E4 -> 588394133 | F6: =F2-F3-F4 -> 494243688 | G6: =G2-G3-G4 -> 575388855 | H6: =H2-H3-H4 -> 585322059 | I6: =I2-I3-I4 -> 578322896 | J6: =J2-J3-J4 -> 640871036 | ... N6: =N2-N3-N4 -> 615910868 | O6: =SUM(C6:N6) -> 6917317336
A7: Marge opérationnelle | B7: % | C7: =IFERROR(C6/C2,0) -> 0.42548644 | D7: =IFERROR(D6/D2,0) -> 0.40796541 | E7: =IFERROR(E6/E2,0) -> 0.38664603 | F7: =IFERROR(F6/F2,0) -> 0.36112154 | G7: =IFERROR(G6/G2,0) -> 0.38394678 | H7: =IFERROR(H6/H2,0) -> 0.39664973 | I7: =IFERROR(I6/I2,0) -> 0.39338637 | J7: =IFERROR(J6/J2,0) -> 0.4141157 | ... O7: =IFERROR(O6/O2,0) -> 0.38997723
