Workbook

Sheet Donnees SOMIDA
A1: DONNEES SOMIDA - PARAMETRES ET REFERENTIELS
A2: Paramètre | B2: Valeur | C2: Unité / devise | D2: Commentaire
A3: Exercice | B3: 2020 | C3: année | D3: Exercice budgétaire
A4: Inflation annuelle | B4: 0.0669 | C4: % | D4: Hypothèse budgétaire
A5: Taux USD/MGA | B5: 4410.51 | C5: MGA/USD | D5: Hypothèse de change
A6: Taux JPY/MGA | B6: 31.47 | C6: MGA/JPY | D6: Hypothèse de change
A7: Augmentation salariale | B7: 0.0766 | C7: % | D7: Hypothèse RH
A8: TVA | B8: 0.2 | C8: % | D8: Paramètre fiscal
A9: Site principal | B9: FORT DAUPHIN | D9: Administration / export
A10: Site production | B10: AMPANDRANDAVA | D10: Production
A12: MARCHES EXPORT
A13: Pays | B13: Entité représentatrice | C13: Devise | D13: Observation
A14: Japon | B14: GOODEIS | C14: JPY | D14: Relation export issue de la correction utilisateur
A15: Russie | B15: ELINAR | C15: USD | D15: Relation export issue de la correction utilisateur
A16: Chine | B16: REPRESENTANT CHINE - A VALIDER | C16: USD | D16: Nom exact à confirmer depuis Données SOMIDA

Sheet Employes
A1: Matricule | B1: Nom simulé | C1: Site | D1: Département | E1: Poste | F1: Salaire base mensuel (MGA) | G1: Prime mensuelle (MGA) | H1: Charges patronales (MGA) | I1: Coût mensuel total (MGA) | J1: Statut
A2: EMP-001 | B2: RABE Hery | C2: AMBOASARY | D2: Direction | E2: Directeur Général | F2: 9355900 | G2: 1142500 | H2: 1688500 | I2: 12636000 | J2: Actif
A3: EMP-002 | B3: RAKOTO Miora | C3: AMBOASARY | D3: Direction | E3: DAF | F3: 6745500 | G3: 670400 | H3: 1196400 | I3: 8920800 | J3: Actif
A4: EMP-003 | B4: ANDRIA Fanja | C4: FORT DAUPHIN | D4: Finance | E4: Chef comptable | F4: 3862100 | G4: 196900 | H4: 705600 | I4: 4986000 | J4: Actif
A5: EMP-004 | B5: RAZAFY Toky | C5: AMPANDRANDAVA | D5: Finance | E5: Comptable | F5: 2356100 | G5: 116100 | H5: 427300 | I5: 3011040 | J5: Actif
A6: EMP-005 | B6: RANDRIA Nirina | C6: FORT DAUPHIN | D6: Finance | E6: Assistant comptable | F6: 1761400 | G6: 89400 | H6: 317500 | I6: 2249280 | J6: Actif
A7: EMP-006 | B7: RATSIM Lova | C7: AMPANDRANDAVA | D7: RH | E7: Responsable RH | F7: 3319800 | G7: 163600 | H7: 587600 | I7: 4242240 | J7: Actif
A8: EMP-007 | B8: RAJAO Aina | C8: FORT DAUPHIN | D8: Commercial | E8: Responsable commercial export | F8: 3727600 | G8: 298200 | H8: 653200 | I8: 4798800 | J8: Actif
A9: EMP-008 | B9: RAMAN Tiana | C9: AMBOASARY | D9: Commercial | E9: Agent export | F9: 2087500 | G9: 248800 | H9: 365300 | I9: 2779920 | J9: Actif
A10: EMP-009 | B10: RAKOTON Zo | C10: AMPANDRANDAVA | D10: Production | E10: Responsable production | F10: 3836000 | G10: 187000 | H10: 689700 | I10: 4808880 | J10: Actif
A11: EMP-010 | B11: RAZAN Mamy | C11: FORT DAUPHIN | D11: Production | E11: Chef d'atelier | F11: 2349800 | G11: 191800 | H11: 430200 | I11: 3129840 | J11: Actif
A12: EMP-011 | B12: RABARY Lalaina | C12: AMPANDRANDAVA | D12: Production | E12: Contrôleur qualité | F12: 1948700 | G12: 99000 | H12: 352600 | I12: 2506320 | J12: Actif
A13: EMP-012 | B13: RAKOTOMALALA Tahina | C13: FORT DAUPHIN | D13: Production | E13: Opérateur traitement | F13: 1270300 | G13: 127500 | H13: 228400 | I13: 1686240 | J13: Actif
... A61: EMP-060 | B61: RAKOTOVONINA Rova | C61: TRANOMARO | D61: RH | E61: Responsable RH | F61: 3390800 | G61: 168600 | H61: 614400 | I61: 4304160 | J61: Actif

Sheet Production
A1: Site | B1: Produit | C1: Unité | D1: Janvier | E1: Février | F1: Mars | G1: Avril | H1: Mai | I1: Juin | J1: Juillet | K1: Août | L1: Septembre | M1: Octobre | N1: Novembre | O1: Décembre | P1: Total annuel
A2: AMPANDRANDAVA | B2: ABR COUPE | C2: tonnes | D2: 79.32 | E2: 70.98 | F2: 70.96 | G2: 63.42 | H2: 63.11 | I2: 80.11 | J2: 66.1 | K2: 79.54 | L2: 81.89 | M2: 80.95 | N2: 68.74 | O2: 69.16 | P2: 848.37
A3: AMPANDRANDAVA | B3: FP1 COUPE | C3: tonnes | D3: 58.79 | E3: 50.61 | F3: 52.15 | G3: 50.76 | H3: 58.54 | I3: 46.29 | J3: 61.62 | K3: 56.8 | L3: 52.7 | M3: 49.85 | N3: 53.01 | O3: 52.44 | P3: 630.72
A4: AMPANDRANDAVA | B4: FP2 COUPE | C4: tonnes | D4: 47.81 | E4: 42.22 | F4: 49.52 | G4: 46.03 | H4: 51.19 | I4: 40.79 | J4: 50.92 | K4: 51.75 | L4: 43.66 | M4: 50.14 | N4: 41.35 | O4: 50.91 | P4: 563.71
A5: AMPANDRANDAVA | B5: TRA | C5: tonnes | D5: 59.89 | E5: 72.01 | F5: 62.34 | G5: 62.81 | H5: 56.25 | I5: 57.66 | J5: 63.39 | K5: 59.32 | L5: 53.76 | M5: 63.03 | N5: 61.55 | O5: 75.05 | P5: 744.92
A6: AMPANDRANDAVA | B6: BSA | C6: tonnes | D6: 38.12 | E6: 43.78 | F6: 46.74 | G6: 41.6 | H6: 45.66 | I6: 36.89 | J6: 41.98 | K6: 45.96 | L6: 38.18 | M6: 40.18 | N6: 41.89 | O6: 35.71 | P6: 493.84
A7: FORT DAUPHIN | B7: ABR COUPE | C7: tonnes | D7: 73.01 | E7: 76.93 | F7: 65.87 | G7: 72.66 | H7: 78.04 | I7: 66.32 | J7: 71.37 | K7: 67.55 | L7: 63.21 | M7: 69.23 | N7: 58.82 | O7: 66.17 | P7: 802.2
A8: FORT DAUPHIN | B8: FP1 COUPE | C8: tonnes | D8: 47.81 | E8: 48.72 | F8: 59.49 | G8: 46.97 | H8: 61.12 | I8: 62.12 | J8: 55.81 | K8: 46.8 | L8: 47.44 | M8: 56.89 | N8: 53.88 | O8: 61.63 | P8: 650.9
A9: FORT DAUPHIN | B9: FP2 COUPE | C9: tonnes | D9: 42.25 | E9: 42.02 | F9: 50.72 | G9: 53.59 | H9: 44.53 | I9: 43.86 | J9: 53.57 | K9: 43.96 | L9: 45.79 | M9: 46.17 | N9: 48.68 | O9: 48.14 | P9: 540.61
A10: FORT DAUPHIN | B10: TRA | C10: tonnes | D10: 54.96 | E10: 71.01 | F10: 57.32 | G10: 59.35 | H10: 63.94 | I10: 57.55 | J10: 74.04 | K10: 65.11 | L10: 61.8 | M10: 69.23 | N10: 61.45 | O10: 67.73 | P10: 753.15
A11: FORT DAUPHIN | B11: BSA | C11: tonnes | D11: 45.4 | E11: 47.62 | F11: 42.2 | G11: 46.28 | H11: 35.46 | I11: 39.56 | J11: 45.97 | K11: 37.98 | L11: 44.48 | M11: 37.55 | N11: 40.11 | O11: 42.07 | P11: 497.16

Sheet Charges
A1: Catégorie | B1: Nature | C1: Site | D1: Unité | E1: Janvier | F1: Février | G1: Mars | H1: Avril | I1: Mai | J1: Juin | K1: Juillet | L1: Août | M1: Septembre | N1: Octobre | O1: Novembre | P1: Décembre | Q1: Total annuel
A2: PRODUCTION | B2: Matières et consommables | C2: AMPANDRANDAVA | D2: MGA | E2: 155924600 | F2: 131088400 | G2: 157133900 | H2: 138400100 | I2: 135926600 | J2: 136366700 | K2: 137335800 | L2: 155223200 | M2: 134944200 | N2: 152639500 | O2: 136298100 | P2: 147204600 | Q2: 1681789600
A3: PRODUCTION | B3: Énergie / électricité | C3: AMPANDRANDAVA | D3: MGA | E3: 50386200 | F3: 44762400 | G3: 50589500 | H3: 49895900 | I3: 51043600 | J3: 54451600 | K3: 52004500 | L3: 46453300 | M3: 42533500 | N3: 40568300 | O3: 49412700 | P3: 52885800 | Q3: 586019300
A4: PRODUCTION | B4: Traitement mica | C4: AMPANDRANDAVA | D4: MGA | E4: 74752600 | F4: 80374300 | G4: 86495200 | H4: 79468100 | I4: 77630200 | J4: 90365500 | K4: 78905400 | L4: 86909200 | M4: 82311700 | N4: 79356000 | O4: 80465100 | P4: 76916200 | Q4: 976475800
A5: PRODUCTION | B5: Maintenance équipements | C5: AMPANDRANDAVA | D5: MGA | E5: 33884700 | F5: 28063300 | G5: 30907800 | H5: 28807300 | I5: 36947100 | J5: 33855200 | K5: 31410400 | L5: 34276400 | M5: 33390500 | N5: 28638500 | O5: 36146000 | P5: 32169600 | Q5: 385425900
A6: PRODUCTION | B6: Emballages | C6: FORT DAUPHIN | D6: MGA | E6: 26620200 | F6: 24321200 | G6: 22099900 | H6: 23481900 | I6: 22596800 | J6: 25893300 | K6: 22466400 | L6: 22643600 | M6: 23769400 | N6: 24335200 | O6: 21547700 | P6: 20634300 | Q6: 290889200
A7: ADMINISTRATION | B7: Télécommunications / Internet | C7: FORT DAUPHIN | D7: MGA | E7: 7585500 | F7: 7612200 | G7: 7065400 | H7: 7249700 | I7: 7671300 | J7: 7173300 | K7: 7907700 | L7: 8166500 | M7: 7838600 | N7: 8328300 | O7: 6949100 | P7: 7272600 | Q7: 92253300
A8: ADMINISTRATION | B8: Assurances | C8: FORT DAUPHIN | D8: MGA | E8: 11600200 | F8: 12666400 | G8: 14189600 | H8: 14533800 | I8: 11237700 | J8: 13094000 | K8: 12323300 | L8: 14424500 | M8: 11493800 | N8: 12003400 | O8: 14284900 | P8: 14890800 | Q8: 162814200
A9: ADMINISTRATION | B9: Honoraires et conseil | C9: FORT DAUPHIN | D9: MGA | E9: 17153700 | F9: 15523700 | G9: 15175200 | H9: 17140000 | I9: 15632000 | J9: 16945000 | K9: 16630300 | L9: 15855300 | M9: 14890600 | N9: 17275200 | O9: 16379600 | P9: 16048700 | Q9: 195456700
A10: LOGISTIQUE | B10: Transport interne | C10: FORT DAUPHIN | D10: MGA | E10: 34368600 | F10: 35550100 | G10: 35907200 | H10: 38657300 | I10: 35345100 | J10: 41349300 | K10: 34437100 | L10: 37825700 | M10: 40959800 | N10: 39251600 | O10: 35701300 | P10: 36760200 | Q10: 449616600
A11: LOGISTIQUE | B11: Magasinage / manutention | C11: FORT DAUPHIN | D11: MGA | E11: 20312500 | F11: 19062700 | G11: 23743000 | H11: 22870400 | I11: 24301800 | J11: 23737900 | K11: 22388100 | L11: 20962400 | M11: 22947200 | N11: 22825300 | O11: 21705100 | P11: 24558700 | Q11: 260112600
A12: FISCAL | B12: Impôts et taxes | C12: FORT DAUPHIN | D12: MGA | E12: 28747200 | F12: 25525000 | G12: 23412500 | H12: 25267700 | I12: 28588200 | J12: 27684000 | K12: 23500300 | L12: 29955200 | M12: 28725800 | N12: 24738900 | O12: 26267600 | P12: 30768500 | Q12: 309718000
A13: FINANCE | B13: Frais bancaires | C13: FORT DAUPHIN | D13: MGA | E13: 11346100 | F13: 9589300 | G13: 10591700 | H13: 12075400 | I13: 11690300 | J13: 10464400 | K13: 10613100 | L13: 10850600 | M13: 11778000 | N13: 10781300 | O13: 11339200 | P13: 12485300 | Q13: 137119000
A14: SECURITE | B14: Gardiennage / sécurité | C14: AMPANDRANDAVA | D14: MGA | E14: 14397300 | F14: 14664800 | G14: 13981000 | H14: 16058200 | I14: 15450500 | J14: 15436800 | K14: 14877200 | L14: 14276900 | M14: 15034000 | N14: 14629700 | O14: 14625300 | P14: 13679300 | Q14: 174015200

Sheet Exportations
A1: SOMIDA — TABLEAU DE BORD DES EXPORTATIONS 2025
A2: Pilotage DAF • Japon / Russie / Chine • Suivi mensuel des volumes, devises et chiffre d’affaires
A4: VOLUME EXPORTÉ (t) | D4: CA EXPORT (MGA) | G4: CA JAPON (MGA) | J4: CA RUSSIE (MGA) | M4: CA CHINE (MGA) | P4: MARCHÉS / DEVISES
A5: =SUMIF($E$10:$E$54,"Quantité exportée",$S$10:$S$54) -> 3160.98 | D5: =SUMIF($E$10:$E$54,"Chiffre d'affaires MGA",$S$10:$S$54) -> 19024357328 | G5: =SUMIFS($S$10:$S$54,$A$10:$A$54,"Japon",$E$10:$E$54,"Chiffre d'affaires MGA") -> 5885836491 | J5: =SUMIFS($S$10:$S$54,$A$10:$A$54,"Russie",$E$10:$E$54,"Chiffre d'affaires MGA") -> 6497377284 | M5: =SUMIFS($S$10:$S$54,$A$10:$A$54,"Chine",$E$10:$E$54,"Chiffre d'affaires MGA") -> 6641143553 | P5: 3 pays • JPY / USD
A7: DÉTAIL MENSUEL DES EXPORTATIONS PAR MARCHÉ, REPRÉSENTANT ET PRODUIT
A9: Pays | B9: Entité représentatrice | C9: Produit | D9: Devise | E9: Indicateur | F9: Unité | G9: Janvier | H9: Février | I9: Mars | J9: Avril | K9: Mai | L9: Juin | M9: Juillet | N9: Août | O9: Septembre | P9: Octobre | Q9: Novembre | R9: Décembre | S9: Total annuel
A10: Japon | B10: GOODEIS | C10: ABR COUPE | D10: JPY | E10: Quantité exportée | F10: tonnes | G10: 20.47 | H10: 27.31 | I10: 23.79 | J10: 20.56 | K10: 18.33 | L10: 23.84 | M10: 21.79 | N10: 22.93 | O10: 21.41 | P10: 17.71 | Q10: 15.28 | R10: 22.56 | S10: 268.25
A11: Japon | B11: GOODEIS | C11: ABR COUPE | D11: JPY | E11: Chiffre d'affaires devise | F11: JPY | G11: 4155100 | H11: 5016900 | I11: 4576900 | J11: 3788900 | K11: 3377100 | L11: 4464300 | M11: 4084600 | N11: 4447300 | O11: 3807800 | P11: 3487100 | Q11: 3079100 | R11: 4353200 | S11: 50866906
A12: Japon | B12: GOODEIS | C12: ABR COUPE | D12: JPY | E12: Chiffre d'affaires MGA | F12: MGA | G12: 128452800 | H12: 154351600 | I12: 135595400 | J12: 115604700 | K12: 106080400 | L12: 142578800 | M12: 126219500 | N12: 137491000 | O12: 125042500 | P12: 107626000 | Q12: 91520100 | R12: 131072500 | S12: 1587047475
A13: Japon | B13: GOODEIS | C13: FP1 COUPE | D13: JPY | E13: Quantité exportée | F13: tonnes | G13: 12.74 | H13: 15.27 | I13: 13.32 | J13: 18.14 | K13: 18.19 | L13: 19.55 | M13: 16.65 | N13: 15.06 | O13: 19.88 | P13: 14.25 | Q13: 14.59 | R13: 20.77 | S13: 210.32
A14: Japon | B14: GOODEIS | C14: FP1 COUPE | D14: JPY | E14: Chiffre d'affaires devise | F14: JPY | G14: 2136300 | H14: 2710300 | I14: 2282900 | J14: 3132100 | K14: 3127900 | L14: 3697700 | M14: 2843200 | N14: 2711100 | O14: 3378600 | P14: 2570000 | Q14: 2508600 | R14: 3833700 | S14: 36863838
A15: Japon | B15: GOODEIS | C15: FP1 COUPE | D15: JPY | E15: Chiffre d'affaires MGA | F15: MGA | G15: 66894200 | H15: 83261500 | I15: 75581800 | J15: 96295400 | K15: 100104200 | L15: 108873500 | M15: 88481500 | N15: 83123300 | O15: 103196100 | P15: 77201700 | Q15: 77085800 | R15: 115809100 | S15: 1150151746
A16: Japon | B16: GOODEIS | C16: FP2 COUPE | D16: JPY | E16: Quantité exportée | F16: tonnes | G16: 10.94 | H16: 12.45 | I16: 15.07 | J16: 15.49 | K16: 13.67 | L16: 12.94 | M16: 18.34 | N16: 12.35 | O16: 12.85 | P16: 15.23 | Q16: 16.69 | R16: 13.07 | S16: 179.48
A17: Japon | B17: GOODEIS | C17: FP2 COUPE | D17: JPY | E17: Chiffre d'affaires devise | F17: JPY | G17: 1944500 | H17: 2224700 | I17: 2624600 | J17: 2632000 | K17: 2259100 | L17: 2188400 | M17: 3105200 | N17: 2093300 | O17: 2206700 | P17: 2567000 | Q17: 2748800 | R17: 2279700 | S17: 30354555
A18: Japon | B18: GOODEIS | C18: FP2 COUPE | D18: JPY | E18: Chiffre d'affaires MGA | F18: MGA | G18: 62271100 | H18: 66346700 | I18: 85085000 | J18: 86228200 | K18: 69556400 | L18: 68122500 | M18: 93141200 | N18: 62160900 | O18: 70850000 | P18: 76889300 | Q18: 86703300 | R18: 72051300 | S18: 947062116
A19: Japon | B19: GOODEIS | C19: TRA | D19: JPY | E19: Quantité exportée | F19: tonnes | G19: 21.38 | H19: 23.87 | I19: 14.18 | J19: 23.83 | K19: 15.98 | L19: 23.73 | M19: 15.2 | N19: 23 | O19: 23.25 | P19: 25 | Q19: 24.92 | R19: 19.41 | S19: 265.95
A20: Japon | B20: GOODEIS | C20: TRA | D20: JPY | E20: Chiffre d'affaires devise | F20: JPY | G20: 3911500 | H20: 4229300 | I20: 2601600 | J20: 4122900 | K20: 3004400 | L20: 4180900 | M20: 2734100 | N20: 3960300 | O20: 4227100 | P20: 4330600 | Q20: 4557600 | R20: 3320600 | S20: 48522578
A21: Japon | B21: GOODEIS | C21: TRA | D21: JPY | E21: Chiffre d'affaires MGA | F21: MGA | G21: 115813000 | H21: 139376100 | I21: 83052200 | J21: 128564900 | K21: 93526900 | L21: 127207600 | M21: 85050200 | N21: 130823800 | O21: 134323000 | P21: 142570000 | Q21: 142390400 | R21: 104092800 | S21: 1513904417
... A54: Chine | B54: REPRESENTANT CHINE - A VALIDER | C54: BSA | D54: USD | E54: Chiffre d'affaires MGA | F54: MGA | G54: 54275800 | H54: 68144400 | I54: 75497900 | J54: 68882000 | K54: 70413300 | L54: 56771000 | M54: 72008600 | N54: 71325900 | O54: 53041600 | P54: 50947900 | Q54: 78066500 | R54: 61503500 | S54: 831048463

Sheet Frais Export
A1: Pays | B1: Entité représentatrice | C1: Nature frais | D1: Unité | E1: Janvier | F1: Février | G1: Mars | H1: Avril | I1: Mai | J1: Juin | K1: Juillet | L1: Août | M1: Septembre | N1: Octobre | O1: Novembre | P1: Décembre | Q1: Total annuel
A2: Japon | B2: GOODEIS | C2: Transport local | D2: MGA | E2: 13588600 | F2: 13187500 | G2: 15650700 | H2: 14347000 | I2: 15027100 | J2: 14906400 | K2: 13882900 | L2: 14841200 | M2: 15698600 | N2: 12650200 | O2: 12337700 | P2: 16030600 | Q2: 177840800
A3: Japon | B3: GOODEIS | C3: Transit & documents | D3: MGA | E3: 7320100 | F3: 7314800 | G3: 7172300 | H3: 7257300 | I3: 7116400 | J3: 6289700 | K3: 6415200 | L3: 6957100 | M3: 6357300 | N3: 6435200 | O3: 5922700 | P3: 7598000 | Q3: 81615300
A4: Japon | B4: GOODEIS | C4: Manutention portuaire | D4: MGA | E4: 7675800 | F4: 9646400 | G4: 7931000 | H4: 9017200 | I4: 8272500 | J4: 7565900 | K4: 10211200 | L4: 7839100 | M4: 7678400 | N4: 9330700 | O4: 8396900 | P4: 7707500 | Q4: 105124000
A5: Japon | B5: GOODEIS | C5: Fret international | D5: MGA | E5: 53004200 | F5: 44224300 | G5: 49740100 | H5: 53945100 | I5: 51002400 | J5: 52067900 | K5: 43779300 | L5: 51663000 | M5: 48481900 | N5: 45440200 | O5: 40902000 | P5: 54124200 | Q5: 589811900
A6: Japon | B6: GOODEIS | C6: Assurance transport | D6: MGA | E6: 4425600 | F6: 4586800 | G6: 4053700 | H6: 4219300 | I6: 4125400 | J6: 4480300 | K6: 4427100 | L6: 4682000 | M6: 4297700 | N6: 4073800 | O6: 4483900 | P6: 4999900 | Q6: 51868200
A7: Japon | B7: GOODEIS | C7: Frais bancaires export | D7: MGA | E7: 3830300 | F7: 3114000 | G7: 2863800 | H7: 3036400 | I7: 2812700 | J7: 3501800 | K7: 3358500 | L7: 2920300 | M7: 3930900 | N7: 3556500 | O7: 3726500 | P7: 3490600 | Q7: 39117200
A8: Russie | B8: ELINAR | C8: Transport local | D8: MGA | E8: 15247400 | F8: 13922200 | G8: 14833200 | H8: 16016000 | I8: 13334500 | J8: 13963300 | K8: 13186500 | L8: 17053800 | M8: 15174900 | N8: 14715800 | O8: 14892800 | P8: 13446700 | Q8: 175267500
A9: Russie | B9: ELINAR | C9: Transit & documents | D9: MGA | E9: 7634500 | F9: 6363300 | G9: 6099200 | H9: 6759000 | I9: 6582500 | J9: 6361600 | K9: 7064800 | L9: 6269600 | M9: 6151000 | N9: 7405900 | O9: 8026900 | P9: 6500100 | Q9: 80545100
A10: Russie | B10: ELINAR | C10: Manutention portuaire | D10: MGA | E10: 10196100 | F10: 8767200 | G10: 9004300 | H10: 8272800 | I10: 8517500 | J10: 10460200 | K10: 10599100 | L10: 10566300 | M10: 10277600 | N10: 10203400 | O10: 8290400 | P10: 8479400 | Q10: 114725000
A11: Russie | B11: ELINAR | C11: Fret international | D11: MGA | E11: 60212700 | F11: 47884600 | G11: 53296600 | H11: 48386000 | I11: 51180200 | J11: 61666200 | K11: 47248600 | L11: 57219900 | M11: 47646500 | N11: 54615000 | O11: 52665500 | P11: 52042300 | Q11: 660243400
A12: Russie | B12: ELINAR | C12: Assurance transport | D12: MGA | E12: 5567300 | F12: 5355300 | G12: 5428800 | H12: 5251200 | I12: 4677400 | J12: 5870600 | K12: 5063800 | L12: 4848300 | M12: 5437600 | N12: 5691800 | O12: 5738100 | P12: 4939100 | Q12: 62356100
A13: Russie | B13: ELINAR | C13: Frais bancaires export | D13: MGA | E13: 4053200 | F13: 3662700 | G13: 3934100 | H13: 4107900 | I13: 3688600 | J13: 2921100 | K13: 3863700 | L13: 4019400 | M13: 3333300 | N13: 3908600 | O13: 3223700 | P13: 4154700 | Q13: 45417700
... A19: Chine | B19: REPRESENTANT CHINE - A VALIDER | C19: Frais bancaires export | D19: MGA | E19: 2550400 | F19: 2577600 | G19: 3252900 | H19: 2829500 | I19: 3401400 | J19: 3247200 | K19: 2863000 | L19: 2512900 | M19: 3250200 | N19: 2996000 | O19: 2574500 | P19: 3043100 | Q19: 35706300

Sheet Synthese
A1: Indicateur | B1: Unité | C1: Janvier | D1: Février | E1: Mars | F1: Avril | G1: Mai | H1: Juin | I1: Juillet | J1: Août | K1: Septembre | L1: Octobre | M1: Novembre | N1: Décembre | O1: Total annuel
A2: CA export | B2: MGA | C2: =SUMIF(Exportations!$E$2:$E$54,"Chiffre d'affaires MGA",Exportations!$G$2:$G$54) -> 1464046700 | D2: =SUMIF(Exportations!$E$2:$E$54,"Chiffre d'affaires MGA",Exportations!$H$2:$H$54) -> 1462171600 | E2: =SUMIF(Exportations!$E$2:$E$54,"Chiffre d'affaires MGA",Exportations!$I$2:$I$54) -> 1418207900 | F2: =SUMIF(Exportations!$E$2:$E$54,"Chiffre d'affaires MGA",Exportations!$J$2:$J$54) -> 1500051200 | G2: =SUMIF(Exportations!$E$2:$E$54,"Chiffre d'affaires MGA",Exportations!$K$2:$K$54) -> 1541117400 | H2: =SUMIF(Exportations!$E$2:$E$54,"Chiffre d'affaires MGA",Exportations!$L$2:$L$54) -> 1450331400 | I2: =SUMIF(Exportations!$E$2:$E$54,"Chiffre d'affaires MGA",Exportations!$M$2:$M$54) -> 1499600000 | J2: =SUMIF(Exportations!$E$2:$E$54,"Chiffre d'affaires MGA",Exportations!$N$2:$N$54) -> 1553690100 | K2: =SUMIF(Exportations!$E$2:$E$54,"Chiffre d'affaires MGA",Exportations!$O$2:$O$54) -> 1492158600 | L2: =SUMIF(Exportations!$E$2:$E$54,"Chiffre d'affaires MGA",Exportations!$P$2:$P$54) -> 1515879800 | M2: =SUMIF(Exportations!$E$2:$E$54,"Chiffre d'affaires MGA",Exportations!$Q$2:$Q$54) -> 1539513500 | N2: =SUMIF(Exportations!$E$2:$E$54,"Chiffre d'affaires MGA",Exportations!$R$2:$R$54) -> 1529086300 | O2: =SUM(C2:N2) -> 17965854500
A3: Charges exploitation | B3: MGA | C3: =SUM(Charges!$E$2:$E$14) -> 487079400 | D3: =SUM(Charges!$F$2:$F$14) -> 448803800 | E3: =SUM(Charges!$G$2:$G$14) -> 491291900 | F3: =SUM(Charges!$H$2:$H$14) -> 473905800 | G3: =SUM(Charges!$I$2:$I$14) -> 474061200 | H3: =SUM(Charges!$J$2:$J$14) -> 496817000 | I3: =SUM(Charges!$K$2:$K$14) -> 464799600 | J3: =SUM(Charges!$L$2:$L$14) -> 497822800 | K3: =SUM(Charges!$M$2:$M$14) -> 470617100 | L3: =SUM(Charges!$N$2:$N$14) -> 475371200 | M3: =SUM(Charges!$O$2:$O$14) -> 471121700 | N3: =SUM(Charges!$P$2:$P$14) -> 486274600 | O3: =SUM(C3:N3) -> 5737966100
A4: Frais export | B4: MGA | C4: =SUM('Frais Export'!$E$2:$E$19) -> 258684400 | D4: =SUM('Frais Export'!$F$2:$F$19) -> 248617500 | E4: =SUM('Frais Export'!$G$2:$G$19) -> 254245400 | F4: =SUM('Frais Export'!$H$2:$H$19) -> 258346500 | G4: =SUM('Frais Export'!$I$2:$I$19) -> 252989700 | H4: =SUM('Frais Export'!$J$2:$J$19) -> 268438500 | I4: =SUM('Frais Export'!$K$2:$K$19) -> 247064600 | J4: =SUM('Frais Export'!$L$2:$L$19) -> 267261200 | K4: =SUM('Frais Export'!$M$2:$M$19) -> 251200300 | L4: =SUM('Frais Export'!$N$2:$N$19) -> 257347100 | M4: =SUM('Frais Export'!$O$2:$O$19) -> 250989100 | N4: =SUM('Frais Export'!$P$2:$P$19) -> 267028100 | O4: =SUM(C4:N4) -> 3082212400
A5: Masse salariale | B5: MGA | C5: 240945120 | D5: 240945120 | E5: 240945120 | F5: 240945120 | G5: 240945120 | H5: 240945120 | I5: 240945120 | J5: 240945120 | K5: 240945120 | L5: 240945120 | M5: 240945120 | N5: 240945120 | O5: 2891341440
A6: Résultat opérationnel | B6: MGA | C6: 259998928 | D6: 324834677 | E6: 156849912 | F6: 329768962 | G6: 286600954 | H6: 265234046 | I6: 294916292 | J6: 249782973 | K6: 365495957 | L6: 348457303 | M6: 374829124 | N6: 309532626 | O6: 4690712314
A7: Marge opérationnelle | B7: % | C7: 0.20482272 | D7: 0.25155965 | E7: 0.13414642 | F7: 0.24982096 | G7: 0.22380852 | H7: 0.20554831 | I7: 0.23227232 | J7: 0.19577014 | K7: 0.26959025 | L7: 0.2601708 | M7: 0.27436184 | N7: 0.23462935 | O7: 0.30171207
